Workbook

Sheet Master
A1: Shop Url | B1: Emails | C1: Meeting title
A2: offdutystore.myshopify.com | B2: {=XLOOKUP(A2,'Meeting Link <> Brand Name'!H:H,'Meeting Link <> Brand Name'!E:E)} -> tejas.k@offduty.in; shahbaaz@offduty.in
A3: cosiq.myshopify.com | B3: {=XLOOKUP(A3,'Meeting Link <> Brand Name'!H:H,'Meeting Link <> Brand Name'!E:E)} -> #N/A
A4: flicka-cosmetics-india.myshopify.com | B4: {=XLOOKUP(A4,'Meeting Link <> Brand Name'!H:H,'Meeting Link <> Brand Name'!E:E)} -> fardeen@trustsignal.io
A5: bombay-shaving.myshopify.com | B5: {=XLOOKUP(A5,'Meeting Link <> Brand Name'!H:H,'Meeting Link <> Brand Name'!E:E)} -> #N/A
A6: makershala.myshopify.com | B6: {=XLOOKUP(A6,'Meeting Link <> Brand Name'!H:H,'Meeting Link <> Brand Name'!E:E)} -> #N/A
A7: 84494d-fc.myshopify.com | B7: {=XLOOKUP(A7,'Meeting Link <> Brand Name'!H:H,'Meeting Link <> Brand Name'!E:E)}
A8: ripped-up-nutritio.myshopify.com | B8: {=XLOOKUP(A8,'Meeting Link <> Brand Name'!H:H,'Meeting Link <> Brand Name'!E:E)} -> himanshu@rippedupnutrition.com
A9: mokobara.myshopify.com | B9: {=XLOOKUP(A9,'Meeting Link <> Brand Name'!H:H,'Meeting Link <> Brand Name'!E:E)} -> #N/A
A10: alpino-in.myshopify.com | B10: {=XLOOKUP(A10,'Meeting Link <> Brand Name'!H:H,'Meeting Link <> Brand Name'!E:E)} -> #N/A
A11: fixderma-skincare.myshopify.com | B11: {=XLOOKUP(A11,'Meeting Link <> Brand Name'!H:H,'Meeting Link <> Brand Name'!E:E)} -> prashant@trustsignal.io
A12: sujatra-sarees.myshopify.com | B12: {=XLOOKUP(A12,'Meeting Link <> Brand Name'!H:H,'Meeting Link <> Brand Name'!E:E)} -> #N/A
A13: deyga-in.myshopify.com | B13: {=XLOOKUP(A13,'Meeting Link <> Brand Name'!H:H,'Meeting Link <> Brand Name'!E:E)}
... A1102: 646888.myshopify.com | B1102: {=XLOOKUP(A1102,'Meeting Link <> Brand Name'!H:H,'Meeting Link <> Brand Name'!E:E)} -> #N/A

Sheet ShopUrl <> Brand Name
A1: name | B1: shopUrl
A2: Backdropsource AU | B2: mousestored.myshopify.com
A3: Interwove | B3: intervowe.myshopify.com
A4: DRUIDS | B4: lachicos.myshopify.com
A5: Odhanon | B5: 671342-2.myshopify.com
A6: Modibodi | B6: moddd-com.myshopify.com
A7: BrustroShop | B7: brustroshop.myshopify.com
A8: Athlos Activewear | B8: goathlos-com.myshopify.com
A9: Ikoho | B9: 204888.myshopify.com
A10: farmerr.in | B10: farmerr-in.myshopify.com
A11: Coolbeds | B11: cool-beds.myshopify.com
A12: Vlado's Himalayan Organics | B12: the-himalayan-organics.myshopify.com
... A830: Arctic Fox India | B830: arctic-fox-india.myshopify.com

Sheet Meeting Link <> Brand Name
A1: company | B1: date | C1: meeting_title | D1: meeting_link | E1: external_attendees | F1: internal_attendees | G1: meeting_id
B2: 46090.417 | C2: Little Rituals x Bitespeed | Bi-weekly Meet | D2: https://meet.google.com/xwc-xuie-qkr | E2: gaurang.narvania@littlerituals.in | F2: ayush.madan@bitespeed.co | G2: 01KK4AFA83YERCAA2DK6JCV9PX | H2: {=XLOOKUP(D2,Sheet1!E:E,Sheet1!B:B)} -> little-rituals-india.myshopify.com | J2: {=XLOOKUP(C2,'Fuzzy Brand Name Match'!B:B,'Fuzzy Brand Name Match'!D:D)} -> #N/A
B3: 46090.417 | C3: Rioware x Bitespeed | D3: https://meet.google.com/fnq-gund-ncg | F3: divya.joshi@bitespeed.co; akshita@bitespeed.co | G3: 01KK8JFBPFYF5GWGE7R32VS6PY | H3: {=XLOOKUP(D3,Sheet1!E:E,Sheet1!B:B)} | J3: {=XLOOKUP(C3,'Fuzzy Brand Name Match'!B:B,'Fuzzy Brand Name Match'!D:D)}
B4: 46090.438 | C4: The Be Life x Bitespeed | Weekly Cadence | D4: https://meet.google.com/ayk-goax-mxe | E4: abhishek.n@thebelife.co; abhishek.b@thebelife.co | F4: ayush.madan@bitespeed.co | G4: 01KK4AFA8AT8WQVPXP66VQT9YJ | H4: {=XLOOKUP(D4,Sheet1!E:E,Sheet1!B:B)} -> thebelife.myshopify.com | J4: {=XLOOKUP(C4,'Fuzzy Brand Name Match'!B:B,'Fuzzy Brand Name Match'!D:D)} -> #N/A
B5: 46090.438 | C5: Zevar : AI Voice Review | D5: https://meet.google.com/kzi-kknq-ehd | E5: akshaydoshi@zevaramaze.com | F5: raashik.kariappa@bitespeed.co | G5: 01KK3Y6PBNVQ82JZ8NVQD1DR5K | H5: {=XLOOKUP(D5,Sheet1!E:E,Sheet1!B:B)} -> #N/A | J5: {=XLOOKUP(C5,'Fuzzy Brand Name Match'!B:B,'Fuzzy Brand Name Match'!D:D)}
B6: 46090.458 | C6: Tangerine Jewelry x Bitespeed : Connect | D6: https://meet.google.com/tce-amqx-jyf | E6: aarohi.s@oxbowcreatives.com | F6: raashik.kariappa@bitespeed.co | G6: 01KK8HF9R0JPTVS50WX693ATTX | H6: {=XLOOKUP(D6,Sheet1!E:E,Sheet1!B:B)} -> #N/A | J6: {=XLOOKUP(C6,'Fuzzy Brand Name Match'!B:B,'Fuzzy Brand Name Match'!D:D)} -> 62aa65.myshopify.com
B7: 46090.458 | C7: Muse Beauty x Bitespeed | D7: https://meet.google.com/fir-cqxv-xxj | F7: divya.joshi@bitespeed.co; rohan@bitespeed.co | G7: 01KK8JAHDSN1QD3142XX7KFVP0 | H7: {=XLOOKUP(D7,Sheet1!E:E,Sheet1!B:B)} -> c66cd2-e0.myshopify.com | J7: {=XLOOKUP(C7,'Fuzzy Brand Name Match'!B:B,'Fuzzy Brand Name Match'!D:D)} -> #N/A
B8: 46090.469 | C8: 9yardz x Bitespeed | Bi-weekly Cadence | D8: https://meet.google.com/mdz-egby-tzy | E8: v.krishnamoorthy.v@gmail.com | F8: ayush.madan@bitespeed.co | G8: 01KK4AFA84CHT5HTKXHAV68WBN | H8: {=XLOOKUP(D8,Sheet1!E:E,Sheet1!B:B)} -> 9yardz.myshopify.com | J8: {=XLOOKUP(C8,'Fuzzy Brand Name Match'!B:B,'Fuzzy Brand Name Match'!D:D)} -> #N/A
B9: 46090.472 | C9: tanmay.dwivedi@bitespeed.co - Mon, 09 Mar 2026 16:51:44 IST - Untitled | D9: https://meet.google.com/rus-mrfs-zmy | G9: 01KK959RDVD0TS76YFABYYFZ60 | H9: {=XLOOKUP(D9,Sheet1!E:E,Sheet1!B:B)} -> therealb-in.myshopify.com | J9: {=XLOOKUP(C9,'Fuzzy Brand Name Match'!B:B,'Fuzzy Brand Name Match'!D:D)} -> #N/A
B10: 46090.479 | C10: Nature Fab Store | D10: https://meet.google.com/zxh-bevc-kjn | F10: akshita@bitespeed.co | G10: 01KK8MABZK3D9TKFZ1C2F3CFW7 | H10: {=XLOOKUP(D10,Sheet1!E:E,Sheet1!B:B)} -> #N/A | J10: {=XLOOKUP(C10,'Fuzzy Brand Name Match'!B:B,'Fuzzy Brand Name Match'!D:D)}
B11: 46090.479 | C11: VIP x Bitespeed | D11: https://meet.google.com/rtp-ohtj-bhz | E11: ananya.dubey@vipbags.com | F11: divyam@bitespeed.co | G11: 01KK7HY1ZCA44DBVZS7XJ3F37Y | H11: {=XLOOKUP(D11,Sheet1!E:E,Sheet1!B:B)} -> #N/A | J11: {=XLOOKUP(C11,'Fuzzy Brand Name Match'!B:B,'Fuzzy Brand Name Match'!D:D)}
B12: 46090.486 | C12: hardik@bitespeed.co - Mon, 09 Mar 2026 17:12:28 IST - Untitled | D12: https://meet.google.com/qqn-yjuk-izw?authuser=0 | G12: 01KK96FR2471VA6620HBNAA2MT | H12: {=XLOOKUP(D12,Sheet1!E:E,Sheet1!B:B)} -> #N/A | J12: {=XLOOKUP(C12,'Fuzzy Brand Name Match'!B:B,'Fuzzy Brand Name Match'!D:D)}
B13: 46090.49 | C13: Right4paws x Bitespeed | Trial Kickoff | D13: https://meet.google.com/yue-gcxt-ffq | E13: johan@petprakalp.com; tahaniyat@voynicmedia.com; tharun@voynicmedia.com | F13: divya.joshi@bitespeed.co; prateek.gautam@bitespeed.co; suhasini@bitespeed.co; sakar.shubham@bitespeed.co | G13: 01KK95ZAXRSBEF1RG9XR325BEH | H13: {=XLOOKUP(D13,Sheet1!E:E,Sheet1!B:B)} -> #N/A | J13: {=XLOOKUP(C13,'Fuzzy Brand Name Match'!B:B,'Fuzzy Brand Name Match'!D:D)}
B14: 46090.49 | C14: Nutristar x Bitespeed | Weekly Cadence | D14: https://meet.google.com/akg-byyh-mfm | E14: kunal@nutristar.in; shivam@nutristar.in; mohit@nutristar.in | F14: ayush.madan@bitespeed.co | G14: 01KK4AFAFMN4DTKXAYFDMH9HMA | H14: {=XLOOKUP(D14,Sheet1!E:E,Sheet1!B:B)} -> 7e2377-6b.myshopify.com | J14: {=XLOOKUP(C14,'Fuzzy Brand Name Match'!B:B,'Fuzzy Brand Name Match'!D:D)} -> #N/A
B15: 46090.5 | C15: The Clothing Factory - Discussion | D15: https://meet.google.com/rvq-wfsx-dpw | F15: rohan@bitespeed.co | G15: 01KK8SSME69XZ1JZJQVXSRF05S | H15: {=XLOOKUP(D15,Sheet1!E:E,Sheet1!B:B)} -> #N/A | J15: {=XLOOKUP(C15,'Fuzzy Brand Name Match'!B:B,'Fuzzy Brand Name Match'!D:D)} -> the-clothing-factory-shop.myshopify.com
B16: 46090.51 | C16: tushita@bitespeed.co - Mon, 09 Mar 2026 17:44:13 IST - Untitled | D16: https://meet.google.com/qso-gpza-oaj | G16: 01KK989W0MSX4JVJ2GJMZR7AYB | H16: {=XLOOKUP(D16,Sheet1!E:E,Sheet1!B:B)} -> #N/A | J16: {=XLOOKUP(C16,'Fuzzy Brand Name Match'!B:B,'Fuzzy Brand Name Match'!D:D)}
B17: 46090.562 | C17: Dominic Smith and navneeth | Bitespeed | D17: https://meet.google.com/wdh-waym-juq | E17: dom@bisonproducts.co.uk | F17: navneeth@bitespeed.co; arthi@bitespeed.co; sandy.bdr@bitespeed.co; tarrush@bitespeed.co; akshay@bitespeed.co | G17: 01KK4CDMWJ87H5CVDKBE3Y10DJ | H17: {=XLOOKUP(D17,Sheet1!E:E,Sheet1!B:B)} -> #N/A | J17: {=XLOOKUP(C17,'Fuzzy Brand Name Match'!B:B,'Fuzzy Brand Name Match'!D:D)}
B18: 46090.573 | C18: V / Aaryaman | D18: https://meet.google.com/bnn-pxex-qzx | F18: aaryaman.kollara@bitespeed.co; suhasini@bitespeed.co | G18: 01KK9BDEZ0TCZ8BPJDAY4901GB | H18: {=XLOOKUP(D18,Sheet1!E:E,Sheet1!B:B)} -> #N/A | J18: {=XLOOKUP(C18,'Fuzzy Brand Name Match'!B:B,'Fuzzy Brand Name Match'!D:D)}
B19: 46090.573 | C19: Onboarding Sync | D19: https://meet.google.com/awb-zkoa-kor | F19: vidya.v@bitespeed.co; tanul@bitespeed.co; suhasini@bitespeed.co | G19: 01KK9CQN32PGTXC23BWTNH30MG | H19: {=XLOOKUP(D19,Sheet1!E:E,Sheet1!B:B)} -> #N/A | J19: {=XLOOKUP(C19,'Fuzzy Brand Name Match'!B:B,'Fuzzy Brand Name Match'!D:D)}
B20: 46090.625 | C20: L1 Sync - Knowledge + Ticket Context | D20: https://meet.google.com/igp-bamg-wpf | F20: sudar@bitespeed.co; abhinav.aggarwal@bitespeed.co; ujjwal@bitespeed.co; karan@bitespeed.co; adityachoudhury@bitespeed.co; yash@bitespeed.co; arindam@bitespeed.co; aman@bitespeed.co | G20: 01KK4JNAQKRTTHA8BMHA5XFT1T | H20: {=XLOOKUP(D20,Sheet1!E:E,Sheet1!B:B)} -> #N/A | J20: {=XLOOKUP(C20,'Fuzzy Brand Name Match'!B:B,'Fuzzy Brand Name Match'!D:D)}
B21: 46091.25 | C21: Brustro : AI Voice Review | D21: https://meet.google.com/tog-fqqw-zsc | E21: brustro@creativehands.in | F21: raashik.kariappa@bitespeed.co | G21: 01KK8PDEEBR6PMV6ZM7GYATH7X | H21: {=XLOOKUP(D21,Sheet1!E:E,Sheet1!B:B)} -> #N/A | J21: {=XLOOKUP(C21,'Fuzzy Brand Name Match'!B:B,'Fuzzy Brand Name Match'!D:D)}
B22: 46091.271 | C22: Oregion x Bitespeed : Broadcast Ideas | D22: https://meet.google.com/kzc-fkmj-non | E22: info@oregion.in | F22: raashik.kariappa@bitespeed.co | G22: 01KK9BTV3456VJDZ8MY2FXPS03 | H22: {=XLOOKUP(D22,Sheet1!E:E,Sheet1!B:B)} -> #N/A | J22: {=XLOOKUP(C22,'Fuzzy Brand Name Match'!B:B,'Fuzzy Brand Name Match'!D:D)}
B23: 46091.271 | C23: Aguante X BiteSpeed || Weekly Meet | D23: https://meet.google.com/bus-zhbg-sqq | E23: ASLAM BODY BASICS <admin@bodybasics.in> | F23: ayush.madan@bitespeed.co | G23: 01KK688ZK83KCQAAGMYA4K2XSV | H23: {=XLOOKUP(D23,Sheet1!E:E,Sheet1!B:B)} -> aguanteindia.myshopify.com | J23: {=XLOOKUP(C23,'Fuzzy Brand Name Match'!B:B,'Fuzzy Brand Name Match'!D:D)} -> #N/A
B24: 46091.271 | C24: The Secret Of Tea - Market and WA | D24: https://meet.google.com/vic-wwse-nbz | E24: sukanya@thrivom.com | F24: shivam.agarwal@bitespeed.co | G24: 01KK9A0WQWKT5GJRSB5YH2V9KD | H24: {=XLOOKUP(D24,Sheet1!E:E,Sheet1!B:B)} -> #N/A | J24: {=XLOOKUP(C24,'Fuzzy Brand Name Match'!B:B,'Fuzzy Brand Name Match'!D:D)}
B25: 46091.274 | C25: rohan@bitespeed.co - Tue, 10 Mar 2026 12:03:54 IST - Untitled | D25: https://meet.google.com/yif-vsrq-iqw | G25: 01KKB77EA2J1S4PMW44C195F7T | H25: {=XLOOKUP(D25,Sheet1!E:E,Sheet1!B:B)} -> #N/A | J25: {=XLOOKUP(C25,'Fuzzy Brand Name Match'!B:B,'Fuzzy Brand Name Match'!D:D)}
B26: 46091.281 | C26: Yardley - Number onboarding | D26: https://meet.google.com/gfm-vpxk-xhc | F26: rohan@bitespeed.co | G26: 01KK9S461J7R8GM6F1JRY0GS0Z | H26: {=XLOOKUP(D26,Sheet1!E:E,Sheet1!B:B)} -> yardley-london-india.myshopify.com | J26: {=XLOOKUP(C26,'Fuzzy Brand Name Match'!B:B,'Fuzzy Brand Name Match'!D:D)} -> #N/A
B27: 46091.292 | C27: GleuHR x Bitespeed | Number Onboarding | D27: https://meet.google.com/vdm-cbrt-onf | E27: amanpreet@gleuhr.com | F27: ayush.madan@bitespeed.co; rohan@bitespeed.co | G27: 01KK9310DQ48Z3V7MNNY9NCKES | H27: {=XLOOKUP(D27,Sheet1!E:E,Sheet1!B:B)} -> #N/A | J27: {=XLOOKUP(C27,'Fuzzy Brand Name Match'!B:B,'Fuzzy Brand Name Match'!D:D)} -> gleuhr.myshopify.com
B28: 46091.292 | C28: Bitespeed X Neeman's | D28: https://meet.google.com/dzj-uvee-ssq | E28: anamika.k@neemans.com; kaushal@neemans.com; kuldeep@neemans.com; abhinav@neemans.com; shankar.s@neemans.com | F28: prachi.chodha@bitespeed.co | G28: 01KK8XNN5A2A3EF2KZSGE2SA1G | H28: {=XLOOKUP(D28,Sheet1!E:E,Sheet1!B:B)} -> #N/A | J28: {=XLOOKUP(C28,'Fuzzy Brand Name Match'!B:B,'Fuzzy Brand Name Match'!D:D)}
B29: 46091.299 | C29: rohan@bitespeed.co - Tue, 10 Mar 2026 12:42:14 IST - Untitled | D29: https://meet.google.com/gfm-vpxk-xhc | G29: 01KKB9DMCD7HA9BA05YMNB7F3Z | H29: {=XLOOKUP(D29,Sheet1!E:E,Sheet1!B:B)} -> yardley-london-india.myshopify.com | J29: {=XLOOKUP(C29,'Fuzzy Brand Name Match'!B:B,'Fuzzy Brand Name Match'!D:D)} -> #N/A
B30: 46091.312 | C30: Frido X Bitespeed || AI Voice Broadcast | D30: https://meet.google.com/ijk-ywmm-koq | E30: amaan.k@myfrido.com | F30: pravandan.srivastava@bitespeed.co; jaideep@bitespeed.co; divyam@bitespeed.co; ritesh@bitespeed.co | G30: 01KK9AGRMFK81FT2EDKNBMVD9F | H30: {=XLOOKUP(D30,Sheet1!E:E,Sheet1!B:B)} -> #N/A | J30: {=XLOOKUP(C30,'Fuzzy Brand Name Match'!B:B,'Fuzzy Brand Name Match'!D:D)}
B31: 46091.312 | C31: Maskman - WA onboarding | D31: https://meet.google.com/txq-ngrw-okf | E31: vaishnavikhandelwaljpr@gmail.com | F31: shivam.agarwal@bitespeed.co | G31: 01KK9A2M79MYWSFSW2NECEKZBV | H31: {=XLOOKUP(D31,Sheet1!E:E,Sheet1!B:B)} -> #N/A | J31: {=XLOOKUP(C31,'Fuzzy Brand Name Match'!B:B,'Fuzzy Brand Name Match'!D:D)}
B32: 46091.344 | C32: Cyclamen x Bitespeed | D32: https://meet.google.com/shh-xjcf-ihk | F32: divya.joshi@bitespeed.co | G32: 01KKBBNPSGZ08BHAZ2EVGFNSXH | H32: {=XLOOKUP(D32,Sheet1!E:E,Sheet1!B:B)} -> #N/A | J32: {=XLOOKUP(C32,'Fuzzy Brand Name Match'!B:B,'Fuzzy Brand Name Match'!D:D)}
B33: 46091.375 | C33: Ryder's Arena x BiteSpeed | Weekly Meet | D33: https://meet.google.com/edm-ekzn-hpk | E33: tarunsyadav15@gmail.com | F33: ayush.madan@bitespeed.co; nandini@bitespeed.co | G33: 01KJYZP8S902EPMVQ1BQ7HFXY3 | H33: {=XLOOKUP(D33,Sheet1!E:E,Sheet1!B:B)} -> 8cbfb1-7e.myshopify.com | J33: {=XLOOKUP(C33,'Fuzzy Brand Name Match'!B:B,'Fuzzy Brand Name Match'!D:D)} -> #N/A
B34: 46091.396 | C34: L1 KT | ContextTransfer | Complete Handover | D34: https://meet.google.com/krz-jwyj-ptq | F34: sudar@bitespeed.co; harshwardhan@bitespeed.co; abhinav.aggarwal@bitespeed.co; ujjwal@bitespeed.co; karan@bitespeed.co; adityachoudhury@bitespeed.co; nandini@bitespeed.co | G34: 01KK9HN5N30SJHVGMP8WP06FN8 | H34: {=XLOOKUP(D34,Sheet1!E:E,Sheet1!B:B)} -> #N/A | J34: {=XLOOKUP(C34,'Fuzzy Brand Name Match'!B:B,'Fuzzy Brand Name Match'!D:D)}
B35: 46091.396 | C35: Bartisans x Bitespeed | Weekly Meet | D35: https://meet.google.com/ydz-ztwa-oez | E35: social@bartisans.in | F35: ayush.madan@bitespeed.co; sharmi@bitespeed.co | G35: 01KK6G0545WHVWRZZA1NXQEM84 | H35: {=XLOOKUP(D35,Sheet1!E:E,Sheet1!B:B)} -> rtcpl.myshopify.com | J35: {=XLOOKUP(C35,'Fuzzy Brand Name Match'!B:B,'Fuzzy Brand Name Match'!D:D)} -> #N/A
B36: 46091.396 | C36: Bartisans x Bitespeed | D36: https://meet.google.com/hwq-iniw-mxt | F36: ayush.madan@bitespeed.co | G36: 01KKBHTXKQVEWTPMCZ4A13H930 | H36: {=XLOOKUP(D36,Sheet1!E:E,Sheet1!B:B)} -> rtcpl.myshopify.com | J36: {=XLOOKUP(C36,'Fuzzy Brand Name Match'!B:B,'Fuzzy Brand Name Match'!D:D)} -> #N/A
B37: 46091.403 | C37: nandini@bitespeed.co - Tue, 10 Mar 2026 15:11:24 IST - Untitled | D37: https://meet.google.com/krz-jwyj-ptq | G37: 01KKBHYRHKXWXE11YWPN0W67EK | H37: {=XLOOKUP(D37,Sheet1!E:E,Sheet1!B:B)} -> #N/A | J37: {=XLOOKUP(C37,'Fuzzy Brand Name Match'!B:B,'Fuzzy Brand Name Match'!D:D)}
B38: 46091.417 | C38: Bitespeed - Books Closure for FY 2025–26 | D38: https://teams.microsoft.com/l/meetup-join/19:meeting_Y2U4MTM0ZWQtNjM3Ni00MmVhLWJmYWItNTA5OWUyYmMyOWNm@thread.v2/0?context={"Tid":"8870f78b-4e5a-4623-ac14-a96a3c669710","Oid":"7690c45a-bda3-45a7-8d6a-fed4829ab462"} | E38: Kalpesh Jain <kalpesh@m2k.co.in>; Gokulnath.I <gokulnath.i@m2k.co.in>; Om Prakash.K <omprakash.k@m2k.co.in> | F38: vinayak@bitespeed.co; aman@bitespeed.co; mehul@bitespeed.co; parth@bitespeed.co; anish@bitespeed.co | G38: 01KK9F404NWCVXS7Z68D4R8E7V | H38: {=XLOOKUP(D38,Sheet1!E:E,Sheet1!B:B)} -> #N/A | J38: {=XLOOKUP(C38,'Fuzzy Brand Name Match'!B:B,'Fuzzy Brand Name Match'!D:D)}
B39: 46091.427 | C39: Dioste Connect | D39: https://meet.google.com/yxm-zdrx-uxf | E39: dioste10@gmail.com | F39: shivam.agarwal@bitespeed.co | G39: 01KK9A9MXVQX1F8QX8F7PKNMFV | H39: {=XLOOKUP(D39,Sheet1!E:E,Sheet1!B:B)} -> #N/A | J39: {=XLOOKUP(C39,'Fuzzy Brand Name Match'!B:B,'Fuzzy Brand Name Match'!D:D)}
B40: 46091.438 | C40: Luka Originals x Bitespeed | D40: https://meet.google.com/ysr-fcxv-gtx | E40: lukaoriginals2023@gmail.com; business.mail.kapil@gmail.com | F40: divya.joshi@bitespeed.co; rohan@bitespeed.co; mahita.potunuri@bitespeed.co; sakar.shubham@bitespeed.co | G40: 01KK9GVNRT4V8E6C88BVNHXAD4 | H40: {=XLOOKUP(D40,Sheet1!E:E,Sheet1!B:B)} -> #N/A | J40: {=XLOOKUP(C40,'Fuzzy Brand Name Match'!B:B,'Fuzzy Brand Name Match'!D:D)}
B41: 46091.438 | C41: Pretty Pixie x Bitespeed | D41: https://meet.google.com/dzm-vwmu-sni | E41: prachi@prettypixie.com | F41: ayush.madan@bitespeed.co | G41: 01KK6NHVM597VSHB8MYFNM281T | H41: {=XLOOKUP(D41,Sheet1!E:E,Sheet1!B:B)} -> preety-pixie.myshopify.com | J41: {=XLOOKUP(C41,'Fuzzy Brand Name Match'!B:B,'Fuzzy Brand Name Match'!D:D)} -> #N/A
B42: 46091.438 | C42: Caramelly x Bitespeed : AI Voice | D42: https://meet.google.com/quz-ttwu-xhz | E42: shivam@caramelly.in | F42: raashik.kariappa@bitespeed.co | G42: 01KK6MD2VS5Z3YE63VEQ0S6PT0 | H42: {=XLOOKUP(D42,Sheet1!E:E,Sheet1!B:B)} -> inespresso.myshopify.com | J42: {=XLOOKUP(C42,'Fuzzy Brand Name Match'!B:B,'Fuzzy Brand Name Match'!D:D)} -> #N/A
B43: 46091.479 | C43: Chottey Lal x Bitespeed | D43: https://meet.google.com/pvs-yckb-vyf | F43: ayush.madan@bitespeed.co | G43: 01KK6WW6VNMCK6VNPBP2BCTN3Q | H43: {=XLOOKUP(D43,Sheet1!E:E,Sheet1!B:B)} -> chotteylal-sons.myshopify.com | J43: {=XLOOKUP(C43,'Fuzzy Brand Name Match'!B:B,'Fuzzy Brand Name Match'!D:D)} -> #N/A
B44: 46091.479 | C44: Truebrowns - Movement | D44: https://meet.google.com/wgx-bmmy-sov | E44: neelesh.jha@truebrowns.com; shivam.singh@truebrowns.com | F44: shivam.agarwal@bitespeed.co; kaushambhi@bitespeed.co | G44: 01KKBK5VGFE01P3K36MAHNJHYX | H44: {=XLOOKUP(D44,Sheet1!E:E,Sheet1!B:B)} | J44: {=XLOOKUP(C44,'Fuzzy Brand Name Match'!B:B,'Fuzzy Brand Name Match'!D:D)}
B45: 46091.479 | C45: Oracura: CSM Introduction | D45: https://meet.google.com/cah-vunf-zuf | F45: akshita@bitespeed.co; ritesh@bitespeed.co | G45: 01KK9JD6VPMBGQVK86PXPZBBYT | H45: {=XLOOKUP(D45,Sheet1!E:E,Sheet1!B:B)} -> oracura.myshopify.com | J45: {=XLOOKUP(C45,'Fuzzy Brand Name Match'!B:B,'Fuzzy Brand Name Match'!D:D)} -> #N/A
B46: 46091.479 | C46: Burger Bae x Bitespeed : AI Voice | D46: https://meet.google.com/bch-ktin-dko | E46: rohan@burgerbae.in | F46: raashik.kariappa@bitespeed.co | G46: 01KKBFAG1Q2GQ3CJ8C8YBNPMMQ | H46: {=XLOOKUP(D46,Sheet1!E:E,Sheet1!B:B)} -> #N/A | J46: {=XLOOKUP(C46,'Fuzzy Brand Name Match'!B:B,'Fuzzy Brand Name Match'!D:D)}
B47: 46091.5 | C47: iThrive x Bitespeed AI Voice Review | D47: https://meet.google.com/xsg-gwur-svh | E47: pranavkumar@ithrivein.com | F47: raashik.kariappa@bitespeed.co | G47: 01KKBM5MTRE3HRMG81R68HHZC6 | H47: {=XLOOKUP(D47,Sheet1!E:E,Sheet1!B:B)} -> #N/A | J47: {=XLOOKUP(C47,'Fuzzy Brand Name Match'!B:B,'Fuzzy Brand Name Match'!D:D)}
B48: 46091.5 | C48: Fridaycharm - Market | D48: https://meet.google.com/wcg-pjum-ami | E48: hamdan@fridaycharm.com | F48: shivam.agarwal@bitespeed.co | G48: 01KK9A8D6RQ80D8WEMCP68VBGH | H48: {=XLOOKUP(D48,Sheet1!E:E,Sheet1!B:B)} -> #N/A | J48: {=XLOOKUP(C48,'Fuzzy Brand Name Match'!B:B,'Fuzzy Brand Name Match'!D:D)}
B49: 46091.5 | C49: Azhar Sheik and navneeth | Bitespeed | D49: https://meet.google.com/auw-rxqs-fvp | E49: azhar@sweethearticecream.co.uk; sandy.bdr@bitepseed.co | F49: navneeth@bitespeed.co; arthi@bitespeed.co; tarrush@bitespeed.co; akshay@bitespeed.co | G49: 01KK6YTE3XRFKNN5WQFT35TXMV | H49: {=XLOOKUP(D49,Sheet1!E:E,Sheet1!B:B)} -> #N/A | J49: {=XLOOKUP(C49,'Fuzzy Brand Name Match'!B:B,'Fuzzy Brand Name Match'!D:D)}
B50: 46091.5 | C50: Swashaa- Finance Discussions | D50: https://meet.google.com/qsr-ipeb-qod | F50: shivali@bitespeed.co; ritesh@bitespeed.co; aakash@bitespeed.co | G50: 01KK8X7T4X8DCD12PE3AGX5G9D | H50: {=XLOOKUP(D50,Sheet1!E:E,Sheet1!B:B)} -> #N/A | J50: {=XLOOKUP(C50,'Fuzzy Brand Name Match'!B:B,'Fuzzy Brand Name Match'!D:D)} -> swashaa.myshopify.com
B51: 46091.542 | C51: Burger Bae x Bitespeed : AI Voice | D51: https://meet.google.com/bch-ktin-dko | E51: rohan@burgerbae.in | F51: raashik.kariappa@bitespeed.co | G51: 01KKBS49DAKW1M772YDHK9HQCK | H51: {=XLOOKUP(D51,Sheet1!E:E,Sheet1!B:B)} -> #N/A | J51: {=XLOOKUP(C51,'Fuzzy Brand Name Match'!B:B,'Fuzzy Brand Name Match'!D:D)}
B52: 46091.583 | C52: Fridaycharm - Market | D52: https://meet.google.com/wcg-pjum-ami | E52: hamdan@fridaycharm.com | F52: shivam.agarwal@bitespeed.co; samridhi.gandhi@bitespeed.co | G52: 01KKBTWJ7JX65XYX48MWWQA17C | H52: {=XLOOKUP(D52,Sheet1!E:E,Sheet1!B:B)} -> #N/A | J52: {=XLOOKUP(C52,'Fuzzy Brand Name Match'!B:B,'Fuzzy Brand Name Match'!D:D)}
B53: 46092.247 | C53: AI-Driven Abandoned Cart Recovery Strategy | D53: https://meet.google.com/jia-hwcr-tmp | G53: 01KKDQB27V1TW02PRX4HFX486E | H53: {=XLOOKUP(D53,Sheet1!E:E,Sheet1!B:B)} -> #N/A | J53: {=XLOOKUP(C53,'Fuzzy Brand Name Match'!B:B,'Fuzzy Brand Name Match'!D:D)}
B54: 46092.25 | C54: Emcure x Bitspeed | Arth New number - Galact Catalgoue Integration | D54: https://meet.google.com/fzv-azwq-zzy | E54: bhavik.karwat@emcure.com | F54: ayush.madan@bitespeed.co | G54: 01KKBKAZY8KQ4P5X1SHQEDQ7GV | H54: {=XLOOKUP(D54,Sheet1!E:E,Sheet1!B:B)} -> #N/A | J54: {=XLOOKUP(C54,'Fuzzy Brand Name Match'!B:B,'Fuzzy Brand Name Match'!D:D)}
B55: 46092.271 | C55: The Secret of Tea - Marketing DB | D55: https://meet.google.com/vfp-vves-unf | E55: sukanya@thrivom.com | F55: shivam.agarwal@bitespeed.co; samridhi.gandhi@bitespeed.co | G55: 01KKB8E0HSCRQJZMH01KDE8GDE | H55: {=XLOOKUP(D55,Sheet1!E:E,Sheet1!B:B)} -> #N/A | J55: {=XLOOKUP(C55,'Fuzzy Brand Name Match'!B:B,'Fuzzy Brand Name Match'!D:D)}
B56: 46092.271 | C56: Millet x Bitespeed : AI Voice | D56: https://meet.google.com/mfo-xznj-awd | E56: harsha@milletamma.com | F56: raashik.kariappa@bitespeed.co | G56: 01KK9DFASFW7B9364WFDPPWE6G | H56: {=XLOOKUP(D56,Sheet1!E:E,Sheet1!B:B)} -> millet-amma-store.myshopify.com | J56: {=XLOOKUP(C56,'Fuzzy Brand Name Match'!B:B,'Fuzzy Brand Name Match'!D:D)} -> #N/A
B57: 46092.271 | C57: Sutra x Bitespeed | Weekly Meet | D57: https://meet.google.com/xhh-phsj-xxn | E57: director@prishtextileindia.com | F57: ayush.madan@bitespeed.co | G57: 01KK8TNPPSDAZR95VV9GJX4JKK | H57: {=XLOOKUP(D57,Sheet1!E:E,Sheet1!B:B)} -> the-sutra-clothing.myshopify.com | J57: {=XLOOKUP(C57,'Fuzzy Brand Name Match'!B:B,'Fuzzy Brand Name Match'!D:D)} -> #N/A
B58: 46092.292 | C58: FMC X Bitespeed - Weekly CatchUp | D58: https://meet.google.com/epg-hvnc-rqa | E58: ameya@fixmycurls.com; business@fixmycurls.com | F58: aditya@bitespeed.co; divyam@bitespeed.co | G58: 01KK99G1ZP8BVRMP6QM8JGR4KE | H58: {=XLOOKUP(D58,Sheet1!E:E,Sheet1!B:B)} -> fix-my-curls.myshopify.com | J58: {=XLOOKUP(C58,'Fuzzy Brand Name Match'!B:B,'Fuzzy Brand Name Match'!D:D)} -> #N/A
B59: 46092.292 | C59: Theater x Bitespeed | Weekly Meet | D59: https://meet.google.com/nmg-ufbq-enq | E59: abhishek@theater.xyz | F59: ayush.madan@bitespeed.co | G59: 01KK8TNPSB7QBPQDE9JTPQK4VQ | H59: {=XLOOKUP(D59,Sheet1!E:E,Sheet1!B:B)} -> #N/A | J59: {=XLOOKUP(C59,'Fuzzy Brand Name Match'!B:B,'Fuzzy Brand Name Match'!D:D)}
B60: 46092.292 | C60: AI Voice : Review Call with Bitespeed | D60: https://meet.google.com/szm-okca-pon | E60: punit@purplemagicstudio.com; mandeep@purplemagicstudio.com | F60: raashik.kariappa@bitespeed.co | G60: 01KKBFG640JBS0NN6CCW5AWJEY | H60: {=XLOOKUP(D60,Sheet1!E:E,Sheet1!B:B)} -> #N/A | J60: {=XLOOKUP(C60,'Fuzzy Brand Name Match'!B:B,'Fuzzy Brand Name Match'!D:D)}
B61: 46092.295 | C61: golap.debnath@bitespeed.co - Wed, 11 Mar 2026 12:33:20 IST - Untitled | D61: https://meet.google.com/ddf-jqay-syx?authuser=0 | G61: 01KKDVA1VAW1HZB8PSK7ZP3ZZH | H61: {=XLOOKUP(D61,Sheet1!E:E,Sheet1!B:B)} -> #N/A | J61: {=XLOOKUP(C61,'Fuzzy Brand Name Match'!B:B,'Fuzzy Brand Name Match'!D:D)}
B62: 46092.312 | C62: Dr Towels x Bitespeed | D62: https://meet.google.com/gos-sdda-axu | E62: manoj.dst1@gmail.com | F62: ayush.madan@bitespeed.co; divyam@bitespeed.co | G62: 01KKC3FHKZHQEDW0CEAPTBAQ88 | H62: {=XLOOKUP(D62,Sheet1!E:E,Sheet1!B:B)} -> drtowel.myshopify.com | J62: {=XLOOKUP(C62,'Fuzzy Brand Name Match'!B:B,'Fuzzy Brand Name Match'!D:D)} -> #N/A
B63: 46092.312 | C63: Varyam online - Marketing DB | D63: https://meet.google.com/fjy-ocmb-yon | E63: varyamonline@gmail.com | F63: shivam.agarwal@bitespeed.co | G63: 01KKBC6QVK6ACF9EXTEZ9KF8DY | H63: {=XLOOKUP(D63,Sheet1!E:E,Sheet1!B:B)} -> 1nqm5a-rk.myshopify.com | J63: {=XLOOKUP(C63,'Fuzzy Brand Name Match'!B:B,'Fuzzy Brand Name Match'!D:D)} -> #N/A
B64: 46092.312 | C64: Craftico | D64: https://meet.google.com/bbz-ncyr-skp | F64: sunanda.das@bitespeed.co | G64: 01KKBAKSMZB50W4DQYE4J27B2G | H64: {=XLOOKUP(D64,Sheet1!E:E,Sheet1!B:B)} -> #N/A | J64: {=XLOOKUP(C64,'Fuzzy Brand Name Match'!B:B,'Fuzzy Brand Name Match'!D:D)} -> 406b58.myshopify.com
B65: 46092.354 | C65: 365 Veda x Bitespeed | Bi-weekly Cadence | D65: https://meet.google.com/owt-eiux-psu | E65: harshit.gohil@365veda.com | F65: ayush.madan@bitespeed.co | G65: 01KK9F8Z4CZ5C7XW0WPSQ9CZP5 | H65: {=XLOOKUP(D65,Sheet1!E:E,Sheet1!B:B)} -> 365vedaofficial.myshopify.com | J65: {=XLOOKUP(C65,'Fuzzy Brand Name Match'!B:B,'Fuzzy Brand Name Match'!D:D)} -> #N/A
B66: 46092.354 | C66: AMPM x Bitespeed : AI Voice Demo | D66: https://meet.google.com/nuj-fjpd-aex | E66: souvik@ampm.in; amit@ampm.in | F66: raashik.kariappa@bitespeed.co | G66: 01KKBW11CY4H6BSH89ERFGAKCN | H66: {=XLOOKUP(D66,Sheet1!E:E,Sheet1!B:B)} -> ampm-online.myshopify.com | J66: {=XLOOKUP(C66,'Fuzzy Brand Name Match'!B:B,'Fuzzy Brand Name Match'!D:D)} -> #N/A
B67: 46092.358 | C67: yash.singh@bitespeed.co - Wed, 11 Mar 2026 14:02:34 IST - Untitled | D67: https://meet.google.com/qop-jyea-yus?authuser=0 | G67: 01KKE0DEKPBWBR1FQAS4XS57HP | H67: {=XLOOKUP(D67,Sheet1!E:E,Sheet1!B:B)} -> #N/A | J67: {=XLOOKUP(C67,'Fuzzy Brand Name Match'!B:B,'Fuzzy Brand Name Match'!D:D)}
B68: 46092.375 | C68: Dipi Treats - Market DB | D68: https://meet.google.com/otm-efqu-avr | E68: sangeetthakur@dipitreats.com | F68: shivam.agarwal@bitespeed.co; samridhi.gandhi@bitespeed.co | G68: 01KKBJXJBNA4PCJ2HXG2Y8CDX1 | H68: {=XLOOKUP(D68,Sheet1!E:E,Sheet1!B:B)} -> #N/A | J68: {=XLOOKUP(C68,'Fuzzy Brand Name Match'!B:B,'Fuzzy Brand Name Match'!D:D)} -> dipi-treats-store.myshopify.com
B69: 46092.396 | C69: Belleza Jewels x Bitespeed | Weekly Cadence | D69: https://meet.google.com/acq-tsuj-nyu | E69: amanjain93@hotmail.com | F69: ayush.madan@bitespeed.co | G69: 01KK9F8XYCRR2HG1457A7RYPYB | H69: {=XLOOKUP(D69,Sheet1!E:E,Sheet1!B:B)} -> #N/A | J69: {=XLOOKUP(C69,'Fuzzy Brand Name Match'!B:B,'Fuzzy Brand Name Match'!D:D)} -> 2f746c-76.myshopify.com
B70: 46092.396 | C70: Deal Booking Demo | FXOnline | D70: https://teams.microsoft.com/l/meetup-join/19:meeting_MzQ4OTNhNTMtOTM2MC00M2M3LTk2ODEtMWVjNTJjZGRhYzJh@thread.v2/0?context={"Tid":"ce6f9430-1d64-4a97-a32d-e92a05a11971","Oid":"77e8d5a1-85b4-40ca-a4c0-c431019cfc6e"} | E70: ANISH BISWAS <biswas.anish@icici.bank.in>; Yusara Shaikh <yusara.shaikh@icici.bank.in> | F70: anish@bitespeed.co | G70: 01KKDVJYG826EW3NJ9T7HEN1TB | H70: {=XLOOKUP(D70,Sheet1!E:E,Sheet1!B:B)} -> #N/A | J70: {=XLOOKUP(C70,'Fuzzy Brand Name Match'!B:B,'Fuzzy Brand Name Match'!D:D)}
B71: 46092.396 | C71: Ahamed | D71: https://meet.google.com/caa-czcu-brf?authuser=0 | G71: 01KKE3NC5JXWV2VX8XH0HTZDWZ | H71: {=XLOOKUP(D71,Sheet1!E:E,Sheet1!B:B)} -> #N/A | J71: {=XLOOKUP(C71,'Fuzzy Brand Name Match'!B:B,'Fuzzy Brand Name Match'!D:D)}
B72: 46092.417 | C72: Sugandhi - Movement | D72: https://meet.google.com/swp-heaf-eov | E72: jaideep1029@gmail.com | F72: shivam.agarwal@bitespeed.co | G72: 01KKBWQV949GAH6WXDG8SGAT2R | H72: {=XLOOKUP(D72,Sheet1!E:E,Sheet1!B:B)} | J72: {=XLOOKUP(C72,'Fuzzy Brand Name Match'!B:B,'Fuzzy Brand Name Match'!D:D)}
B73: 46092.438 | C73: Little Rituals x Bitespeed | D73: https://meet.google.com/nvx-xpiv-jnh | F73: ayush.madan@bitespeed.co; hriday@bitespeed.co | G73: 01KKC4VB2Q4GNTXZGT4B3NE8SX | H73: {=XLOOKUP(D73,Sheet1!E:E,Sheet1!B:B)} -> little-rituals-india.myshopify.com | J73: {=XLOOKUP(C73,'Fuzzy Brand Name Match'!B:B,'Fuzzy Brand Name Match'!D:D)} -> #N/A
B74: 46092.438 | C74: Blingbag - Number Migration | D74: https://meet.google.com/gwo-nosq-mzi | F74: rohan@bitespeed.co | G74: 01KKBJPK6Z7P4W52JF4GS7BK0P | H74: {=XLOOKUP(D74,Sheet1!E:E,Sheet1!B:B)} -> theblingbag.myshopify.com | J74: {=XLOOKUP(C74,'Fuzzy Brand Name Match'!B:B,'Fuzzy Brand Name Match'!D:D)} -> #N/A
B75: 46092.458 | C75: 91 number onboarding | D75: https://meet.google.com/rdd-jyvb-nif | F75: anees.mohammed@bitespeed.co | G75: 01KKE8TD6NXCCDFWVJZGDVTTRN | H75: {=XLOOKUP(D75,Sheet1!E:E,Sheet1!B:B)} -> athomstore.myshopify.com | J75: {=XLOOKUP(C75,'Fuzzy Brand Name Match'!B:B,'Fuzzy Brand Name Match'!D:D)} -> #N/A
B76: 46092.458 | C76: Varco Leg Care | Pricing discussion and Journeys | D76: https://meet.google.com/fih-tgpn-zvs | E76: marketplace@varcolegcare.com; ceo@varcolegcare.com; fred@fireflies.ai | F76: prateek.gautam@bitespeed.co; hardik@bitespeed.co | G76: 01KK94QAZ4YBJZ0AEQHQZ0RVPP | H76: {=XLOOKUP(D76,Sheet1!E:E,Sheet1!B:B)} -> #N/A | J76: {=XLOOKUP(C76,'Fuzzy Brand Name Match'!B:B,'Fuzzy Brand Name Match'!D:D)} -> d3fdde.myshopify.com
B77: 46092.469 | C77: khushi@bitespeed.co - Wed, 11 Mar 2026 16:43:38 IST - Untitled | D77: https://meet.google.com/qac-kjsw-ced?authuser=0 | G77: 01KKE9MC307PC3GMEGNT4AP5NZ | H77: {=XLOOKUP(D77,Sheet1!E:E,Sheet1!B:B)} -> #N/A | J77: {=XLOOKUP(C77,'Fuzzy Brand Name Match'!B:B,'Fuzzy Brand Name Match'!D:D)}
B78: 46092.479 | C78: Muscle Garage x Bitespeed | Trial Kick off | D78: https://meet.google.com/bze-qdzk-jzj | F78: shivam.agarwal@bitespeed.co; divya.joshi@bitespeed.co; ayushverma@bitespeed.co; anees.mohammed@bitespeed.co | G78: 01KKBV5YM50P94AMQ5QPYG1KRP | H78: {=XLOOKUP(D78,Sheet1!E:E,Sheet1!B:B)} -> #N/A | J78: {=XLOOKUP(C78,'Fuzzy Brand Name Match'!B:B,'Fuzzy Brand Name Match'!D:D)}
B79: 46092.479 | C79: Dartists x Bitespeed | D79: https://meet.google.com/mgs-ostx-sbv | F79: divya.joshi@bitespeed.co; akshita@bitespeed.co | G79: 01KKDV4YMMMPHPWMSYYWNX7GJY | H79: {=XLOOKUP(D79,Sheet1!E:E,Sheet1!B:B)} -> #N/A | J79: {=XLOOKUP(C79,'Fuzzy Brand Name Match'!B:B,'Fuzzy Brand Name Match'!D:D)}
B80: 46092.483 | C80: yash.singh@bitespeed.co - Wed, 11 Mar 2026 17:07:27 IST - Untitled | D80: https://meet.google.com/ieb-ngsb-mjd?authuser=0 | G80: 01KKEAZZHBQ46NG9E0VE6WVB7F | H80: {=XLOOKUP(D80,Sheet1!E:E,Sheet1!B:B)} -> #N/A | J80: {=XLOOKUP(C80,'Fuzzy Brand Name Match'!B:B,'Fuzzy Brand Name Match'!D:D)}
B81: 46092.49 | C81: Boond Frang - Market DB | D81: https://meet.google.com/fum-aeip-ybg | F81: sunanda.das@bitespeed.co; shivam.agarwal@bitespeed.co | G81: 01KKDS8HPKRCCM51VV16C7XT9G | H81: {=XLOOKUP(D81,Sheet1!E:E,Sheet1!B:B)} -> #N/A | J81: {=XLOOKUP(C81,'Fuzzy Brand Name Match'!B:B,'Fuzzy Brand Name Match'!D:D)}
B82: 46092.493 | C82: Gadget Shieldz X TrustSignal | D82: https://meet.google.com/mzg-wmfq-wzx | F82: akshita@bitespeed.co | G82: 01KKEB8RJT388CS5S9HZ5H07SR | H82: {=XLOOKUP(D82,Sheet1!E:E,Sheet1!B:B)} -> gadget-shieldz.myshopify.com | J82: {=XLOOKUP(C82,'Fuzzy Brand Name Match'!B:B,'Fuzzy Brand Name Match'!D:D)} -> #N/A
B83: 46092.5 | C83: Kaori By Shreya: Webhook Integration | D83: https://meet.google.com/epa-jroy-zgu | F83: akshita@bitespeed.co | G83: 01KKECD26FFQG5S0DBRPWHH6TG | H83: {=XLOOKUP(D83,Sheet1!E:E,Sheet1!B:B)} -> kaoribyshreya.myshopify.com | J83: {=XLOOKUP(C83,'Fuzzy Brand Name Match'!B:B,'Fuzzy Brand Name Match'!D:D)} -> #N/A
B84: 46092.521 | C84: yash.singh@bitespeed.co - Wed, 11 Mar 2026 18:01:09 IST - Untitled | D84: https://meet.google.com/max-ndwo-tcy?authuser=0 | G84: 01KKEE29S76R3XMH2GCJHNG37F | H84: {=XLOOKUP(D84,Sheet1!E:E,Sheet1!B:B)} -> #N/A | J84: {=XLOOKUP(C84,'Fuzzy Brand Name Match'!B:B,'Fuzzy Brand Name Match'!D:D)}
B85: 46092.521 | C85: Introductory chat with Tushita | BiteSpeed (Vinod Kota) | D85: https://meet.google.com/umo-hvwq-jmp | E85: vinodsai41@gmail.com | F85: tushita@bitespeed.co | G85: 01KKEDZBVKNGBZA5TB14B0VRTE | H85: {=XLOOKUP(D85,Sheet1!E:E,Sheet1!B:B)} -> #N/A | J85: {=XLOOKUP(C85,'Fuzzy Brand Name Match'!B:B,'Fuzzy Brand Name Match'!D:D)}
B86: 46092.531 | C86: parth.tiwari@bitespeed.co - Wed, 11 Mar 2026 18:16:38 IST - Untitled | D86: https://meet.google.com/uun-wugc-inf | G86: 01KKEEYN84N1H6ZV72C582690X | H86: {=XLOOKUP(D86,Sheet1!E:E,Sheet1!B:B)} -> #N/A | J86: {=XLOOKUP(C86,'Fuzzy Brand Name Match'!B:B,'Fuzzy Brand Name Match'!D:D)}
B87: 46092.542 | C87: Bitespeed - Books Closure for FY 2025–26 | D87: https://teams.microsoft.com/l/meetup-join/19:meeting_N2Y0NWJlNjItNWEzMS00YWI5LTgwMWEtYmEwOTU3OWJmNzc5@thread.v2/0?context={"Tid":"8870f78b-4e5a-4623-ac14-a96a3c669710","Oid":"7690c45a-bda3-45a7-8d6a-fed4829ab462"} | E87: Kalpesh Jain <kalpesh@m2k.co.in>; Gokulnath.I <gokulnath.i@m2k.co.in>; Om Prakash.K <omprakash.k@m2k.co.in> | F87: vinayak@bitespeed.co; sampath.kunagu@bitespeed.co; aman@bitespeed.co; mehul@bitespeed.co; parth@bitespeed.co; anish@bitespeed.co | G87: 01KKBQK6K272FM4013AJS60206 | H87: {=XLOOKUP(D87,Sheet1!E:E,Sheet1!B:B)} -> #N/A | J87: {=XLOOKUP(C87,'Fuzzy Brand Name Match'!B:B,'Fuzzy Brand Name Match'!D:D)}
B88: 46092.562 | C88: Maskman Toys - Movement of Number | D88: https://meet.google.com/yfk-aszz-zwp | E88: vaishnavikhandelwaljpr@gmail.com | F88: shivam.agarwal@bitespeed.co | G88: 01KKDVPPSY8844WX46AC2WSNMA | H88: {=XLOOKUP(D88,Sheet1!E:E,Sheet1!B:B)} -> #N/A | J88: {=XLOOKUP(C88,'Fuzzy Brand Name Match'!B:B,'Fuzzy Brand Name Match'!D:D)} -> ed7e3f-cf.myshopify.com
B89: 46092.604 | C89: Mantoro - Movement | D89: https://meet.google.com/zqa-jekm-iwp | F89: shivam.agarwal@bitespeed.co | G89: 01KKE886K1A3GEQREXBFGKAEVN | H89: {=XLOOKUP(D89,Sheet1!E:E,Sheet1!B:B)} -> 7zvmuf-x8.myshopify.com | J89: {=XLOOKUP(C89,'Fuzzy Brand Name Match'!B:B,'Fuzzy Brand Name Match'!D:D)} -> #N/A
B90: 46092.615 | C90: nandini@bitespeed.co - Wed, 11 Mar 2026 20:14:18 IST - Untitled | D90: https://meet.google.com/pyh-jcke-xwm?authuser=0 | G90: 01KKENP4C6GX2SYASJN95XKJDD | H90: {=XLOOKUP(D90,Sheet1!E:E,Sheet1!B:B)} -> #N/A | J90: {=XLOOKUP(C90,'Fuzzy Brand Name Match'!B:B,'Fuzzy Brand Name Match'!D:D)}
B91: 46092.625 | C91: L1 Sync - Knowledge + Ticket Context | D91: https://meet.google.com/igp-bamg-wpf | F91: sudar@bitespeed.co; abhinav.aggarwal@bitespeed.co; ujjwal@bitespeed.co; karan@bitespeed.co; adityachoudhury@bitespeed.co; yash@bitespeed.co; arindam@bitespeed.co; aman@bitespeed.co | G91: 01KK9QES4XJSBK25W35TDK2JSQ | H91: {=XLOOKUP(D91,Sheet1!E:E,Sheet1!B:B)} -> #N/A | J91: {=XLOOKUP(C91,'Fuzzy Brand Name Match'!B:B,'Fuzzy Brand Name Match'!D:D)}
B92: 46093.229 | C92: 1lessidot - Number transfer | D92: https://meet.google.com/wba-jmht-vqo | E92: manish@1lessidiot.com | F92: shivam.agarwal@bitespeed.co | G92: 01KKDY6ZQ9QSZA4J6GWZ5X2A24 | H92: {=XLOOKUP(D92,Sheet1!E:E,Sheet1!B:B)} -> #N/A | J92: {=XLOOKUP(C92,'Fuzzy Brand Name Match'!B:B,'Fuzzy Brand Name Match'!D:D)}
B93: 46093.229 | C93: Soul Works x Bitespeed : AI Voice | D93: https://meet.google.com/nyx-ufjt-tqj | E93: karima.soulworks.co@gmail.com | F93: raashik.kariappa@bitespeed.co | G93: 01KKE4RHCYMR8HV586TMFYQVFZ | H93: {=XLOOKUP(D93,Sheet1!E:E,Sheet1!B:B)} -> #N/A | J93: {=XLOOKUP(C93,'Fuzzy Brand Name Match'!B:B,'Fuzzy Brand Name Match'!D:D)}
B94: 46093.25 | C94: Savyo x Bitespeed : Connect | D94: https://meet.google.com/mxy-zfgd-idq | E94: preetishsimhadri321@gmail.com | F94: raashik.kariappa@bitespeed.co | G94: 01KKG7HYW1E0024Q6KNCM1X96D | H94: {=XLOOKUP(D94,Sheet1!E:E,Sheet1!B:B)} -> #N/A | J94: {=XLOOKUP(C94,'Fuzzy Brand Name Match'!B:B,'Fuzzy Brand Name Match'!D:D)} -> x90ykt-4m.myshopify.com
B95: 46093.271 | C95: Gadget Shieldz | D95: https://meet.google.com/gwj-hjzi-kdd | F95: akshita@bitespeed.co | G95: 01KKE6NCMA5NCFWVV2V82AV23F | H95: {=XLOOKUP(D95,Sheet1!E:E,Sheet1!B:B)} -> gadget-shieldz.myshopify.com | J95: {=XLOOKUP(C95,'Fuzzy Brand Name Match'!B:B,'Fuzzy Brand Name Match'!D:D)} -> #N/A
B96: 46093.285 | C96: ayush.madan@bitespeed.co - Thu, 12 Mar 2026 12:17:54 IST - Untitled | D96: https://meet.google.com/ifh-mngw-hee | G96: 01KKGCTH3K17VG7CQEBS98Y7BX | H96: {=XLOOKUP(D96,Sheet1!E:E,Sheet1!B:B)} -> kicksmachinetest.myshopify.com | J96: {=XLOOKUP(C96,'Fuzzy Brand Name Match'!B:B,'Fuzzy Brand Name Match'!D:D)} -> #N/A
B97: 46093.312 | C97: Bigbanana - Review | D97: https://meet.google.com/aja-dbyn-tvb | E97: deepak@donovanapparels.com | F97: shivam.agarwal@bitespeed.co; yash.singh@bitespeed.co | G97: 01KKGDHSF4YK4725YDFXSRJH0Y | H97: {=XLOOKUP(D97,Sheet1!E:E,Sheet1!B:B)} -> #N/A | J97: {=XLOOKUP(C97,'Fuzzy Brand Name Match'!B:B,'Fuzzy Brand Name Match'!D:D)} -> bigbanana-online.myshopify.com
B98: 46093.312 | C98: Muun Home x Bitespeed : AI Voice Demo | D98: https://meet.google.com/cxf-fstu-hge | E98: jayant@muunhome.com | F98: raashik.kariappa@bitespeed.co | G98: 01KKBSWEZ6Q6JCXPGSTVCZNR7X | H98: {=XLOOKUP(D98,Sheet1!E:E,Sheet1!B:B)} -> #N/A | J98: {=XLOOKUP(C98,'Fuzzy Brand Name Match'!B:B,'Fuzzy Brand Name Match'!D:D)}
B99: 46093.375 | C99: New Shalimar Exports x Bitespeed | D99: https://meet.google.com/eyx-naer-fsw | E99: newshalimarexports@gmail.com; bitespeed@dtcdevelopers.org | F99: divya.joshi@bitespeed.co; arthi@bitespeed.co; navneeth@bitespeed.co; akshay@bitespeed.co | G99: 01KKEP6DJFXGD649B2925ZXMS8 | H99: {=XLOOKUP(D99,Sheet1!E:E,Sheet1!B:B)} -> #N/A | J99: {=XLOOKUP(C99,'Fuzzy Brand Name Match'!B:B,'Fuzzy Brand Name Match'!D:D)}
B100: 46093.396 | C100: Rioware: Journey Review | D100: https://meet.google.com/aga-urom-eky | F100: akshita@bitespeed.co | G100: 01KKEXP8SMV8JNNKHJ77Q5QDQQ | H100: {=XLOOKUP(D100,Sheet1!E:E,Sheet1!B:B)} | J100: {=XLOOKUP(C100,'Fuzzy Brand Name Match'!B:B,'Fuzzy Brand Name Match'!D:D)}
...

Sheet Sheet6
A1: {=UNIQUE(VSTACK('Meeting Link <> Brand Name'!H:H,'Meeting Link <> Brand Name'!I:I))}
A2: little-rituals-india.myshopify.com
A3: thebelife.myshopify.com
A4: #N/A
A5: c66cd2-e0.myshopify.com
A6: 9yardz.myshopify.com
A7: therealb-in.myshopify.com
A8: 7e2377-6b.myshopify.com
A9: aguanteindia.myshopify.com
A10: yardley-london-india.myshopify.com
A11: 8cbfb1-7e.myshopify.com
A12: rtcpl.myshopify.com
A13: preety-pixie.myshopify.com
A14: inespresso.myshopify.com
A15: chotteylal-sons.myshopify.com
A16: oracura.myshopify.com
... A700: evolve-care-1.myshopify.com

Sheet Fuzzy Brand Name Match
A1: id | B1: title | C1: matchedBrand | D1: shopUrl | E1: tier | F1: score
A2: 1 | B2: Rioware x Bitespeed | E2: 0 | F2: 0.17142857
A3: 2 | B3: Zevar : AI Voice Review | E3: 0 | F3: 0.65
A4: 3 | B4: Tangerine Jewelry x Bitespeed : Connect | C4: Tangerine Bio Jewelry | D4: 62aa65.myshopify.com | E4: 2 | F4: 0.767
A5: 4 | B5: Nature Fab Store | E5: 0 | F5: 0.65
A6: 5 | B6: VIP x Bitespeed | E6: 0 | F6: 0.15
A7: 6 | B7: hardik@bitespeed.co - Mon, 09 Mar 2026 17:12:28 IST - Untitled | E7: 0 | F7: 0.225
A8: 7 | B8: Right4paws x Bitespeed | Trial Kickoff | E8: 0 | F8: 0.25
A9: 8 | B9: The Clothing Factory - Discussion | C9: The Clothing Factory | D9: the-clothing-factory-shop.myshopify.com | E9: 1 | F9: 1
A10: 9 | B10: tushita@bitespeed.co - Mon, 09 Mar 2026 17:44:13 IST - Untitled | E10: 0 | F10: 0.225
A11: 10 | B11: Dominic Smith and navneeth | Bitespeed | E11: 0 | F11: 0.65
A12: 11 | B12: V / Aaryaman | E12: 0 | F12: 0.1875
A13: 12 | B13: Onboarding Sync | E13: 0 | F13: 0.15
A14: 13 | B14: L1 Sync - Knowledge + Ticket Context | E14: 0 | F14: 0.21428571
A15: 14 | B15: Brustro : AI Voice Review | E15: 0 | F15: 0.2
A16: 15 | B16: Oregion x Bitespeed : Broadcast Ideas | E16: 0 | F16: 0.2
A17: 16 | B17: The Secret Of Tea - Market and WA | E17: 0 | F17: 0.53333333
A18: 17 | B18: rohan@bitespeed.co - Tue, 10 Mar 2026 12:03:54 IST - Untitled | E18: 0 | F18: 0.225
A19: 18 | B19: GleuHR x Bitespeed | Number Onboarding | C19: Gleuhr | D19: gleuhr.myshopify.com | E19: 1 | F19: 1
A20: 19 | B20: Bitespeed X Neeman's | E20: 0 | F20: 0.53333333
A21: 20 | B21: Frido X Bitespeed || AI Voice Broadcast | E21: 0 | F21: 0.21428571
A22: 21 | B22: Maskman - WA onboarding | E22: 0 | F22: 0.17142857
A23: 22 | B23: Cyclamen x Bitespeed | E23: 0 | F23: 0.15
A24: 23 | B24: L1 KT | ContextTransfer | Complete Handover | E24: 0 | F24: 0.1875
A25: 24 | B25: nandini@bitespeed.co - Tue, 10 Mar 2026 15:11:24 IST - Untitled | E25: 0 | F25: 0.65
A26: 25 | B26: Bitespeed - Books Closure for FY 2025–26 | E26: 0 | F26: 0.65
A27: 26 | B27: Dioste Connect | E27: 0 | F27: 0.21428571
A28: 27 | B28: Luka Originals x Bitespeed | E28: 0 | F28: 0.23333333
A29: 28 | B29: Truebrowns - Movement | E29: 0 | F29: 0.1875
A30: 29 | B30: Burger Bae x Bitespeed : AI Voice | E30: 0 | F30: 0.65
A31: 30 | B31: iThrive x Bitespeed AI Voice Review | E31: 0 | F31: 0.2
... A33: 32 | B33: Azhar Sheik and navneeth | Bitespeed | E33: 0 | F33: 0.2
A34: 33 | B34: Swashaa- Finance Discussions | C34: Swashaa | D34: swashaa.myshopify.com | E34: 1 | F34: 1
A35: 34 | B35: Burger Bae x Bitespeed : AI Voice | E35: 0 | F35: 0.65
A36: 35 | B36: Fridaycharm - Market | E36: 0 | F36: 0.2
A37: 36 | B37: AI-Driven Abandoned Cart Recovery Strategy | E37: 0 | F37: 0.65
A38: 37 | B38: Emcure x Bitspeed | Arth New number - Galact Catalgoue Integration | E38: 0 | F38: 0.65
A39: 38 | B39: The Secret of Tea - Marketing DB | E39: 0 | F39: 0.53333333
A40: 39 | B40: Theater x Bitespeed | Weekly Meet | E40: 0 | F40: 0.65
A41: 40 | B41: AI Voice : Review Call with Bitespeed | E41: 0 | F41: 0.2
A42: 41 | B42: golap.debnath@bitespeed.co - Wed, 11 Mar 2026 12:33:20 IST - Untitled | E42: 0 | F42: 0.225
A43: 42 | B43: Craftico | C43: CRAFTICO | D43: 406b58.myshopify.com | E43: 1 | F43: 1
A44: 43 | B44: yash.singh@bitespeed.co - Wed, 11 Mar 2026 14:02:34 IST - Untitled | E44: 0 | F44: 0.225
A45: 44 | B45: Dipi Treats - Market DB | C45: Dipi Treats | D45: dipi-treats-store.myshopify.com | E45: 1 | F45: 1
A46: 45 | B46: Belleza Jewels x Bitespeed | Weekly Cadence | C46: Belleza Jewels | D46: 2f746c-76.myshopify.com | E46: 1 | F46: 1
A47: 46 | B47: Deal Booking Demo | FXOnline | E47: 0 | F47: 0.225
A48: 47 | B48: Ahamed | E48: 0 | F48: 0.15
A49: 48 | B49: Sugandhi - Movement | E49: 0 | F49: 0.1875
A50: 49 | B50: Varco Leg Care | Pricing discussion and Journeys | C50: Varco Leg Care | D50: d3fdde.myshopify.com | E50: 1 | F50: 1
A51: 50 | B51: khushi@bitespeed.co - Wed, 11 Mar 2026 16:43:38 IST - Untitled | E51: 0 | F51: 0.225
A52: 51 | B52: Muscle Garage x Bitespeed | Trial Kick off | E52: 0 | F52: 0.25
A53: 52 | B53: Dartists x Bitespeed | E53: 0 | F53: 0.15
A54: 53 | B54: yash.singh@bitespeed.co - Wed, 11 Mar 2026 17:07:27 IST - Untitled | E54: 0 | F54: 0.225
A55: 54 | B55: Boond Frang - Market DB | E55: 0 | F55: 0.24
A56: 55 | B56: yash.singh@bitespeed.co - Wed, 11 Mar 2026 18:01:09 IST - Untitled | E56: 0 | F56: 0.225
A57: 56 | B57: Introductory chat with Tushita | BiteSpeed (Vinod Kota) | E57: 0 | F57: 0.225
A58: 57 | B58: parth.tiwari@bitespeed.co - Wed, 11 Mar 2026 18:16:38 IST - Untitled | E58: 0 | F58: 0.24
A59: 58 | B59: Bitespeed - Books Closure for FY 2025–26 | E59: 0 | F59: 0.65
A60: 59 | B60: Maskman Toys - Movement of Number | C60: Legend of Toys | D60: ed7e3f-cf.myshopify.com | E60: 2 | F60: 0.767
A61: 60 | B61: nandini@bitespeed.co - Wed, 11 Mar 2026 20:14:18 IST - Untitled | E61: 0 | F61: 0.225
A62: 61 | B62: L1 Sync - Knowledge + Ticket Context | E62: 0 | F62: 0.21428571
A63: 62 | B63: 1lessidot - Number transfer | E63: 0 | F63: 0.2
A64: 63 | B64: Soul Works x Bitespeed : AI Voice | E64: 0 | F64: 0.225
A65: 64 | B65: Savyo x Bitespeed : Connect | C65: Savyo | D65: x90ykt-4m.myshopify.com | E65: 1 | F65: 1
A66: 65 | B66: Bigbanana - Review | C66: bigbanana | D66: bigbanana-online.myshopify.com | E66: 1 | F66: 1
A67: 66 | B67: Muun Home x Bitespeed : AI Voice Demo | E67: 0 | F67: 0.65
A68: 67 | B68: New Shalimar Exports x Bitespeed | E68: 0 | F68: 0.21428571
A69: 68 | B69: Rioware: Journey Review | E69: 0 | F69: 0.17142857
A70: 69 | B70: Checkout webhooks | E70: 0 | F70: 0.1875
A71: 70 | B71: AKFD Studio x Bitespeed | E71: 0 | F71: 0.65
A72: 71 | B72: Shivangi Clothing | E72: 0 | F72: 0.65
A73: 72 | B73: Emcure x Bitespeed | Email Integration for CSDB | E73: 0 | F73: 0.53333333
A74: 73 | B74: Agam Living X Bitespeed || New Features | C74: THE LIVING CO. | D74: tlc-new.myshopify.com | E74: 2 | F74: 1
A75: 74 | B75: The Secret of Tea - Support DB | E75: 0 | F75: 0.53333333
A76: 75 | B76: hardik@bitespeed.co - Thu, 12 Mar 2026 17:14:15 IST - Untitled | E76: 0 | F76: 0.65
A77: 76 | B77: support sync | E77: 0 | F77: 0.18
A78: 77 | B78: Shivam / V | E78: 0 | F78: 0.2
A79: 78 | B79: Bitespeed - Books Closure for FY 2025–26 | E79: 0 | F79: 0.65
A80: 79 | B80: Varco Leg Care | Pricing discussion | C80: Varco Leg Care | D80: d3fdde.myshopify.com | E80: 1 | F80: 1
A81: 80 | B81: Cannac x Bitespeed : Connect | C81: Cannac | D81: 88db90-2.myshopify.com | E81: 1 | F81: 1
A82: 81 | B82: Pairie Tales x Bitespeed | E82: 0 | F82: 0.18
A83: 82 | B83: Bitespeed set up for Ireader | E83: 0 | F83: 0.53333333
A84: 83 | B84: akshita@bitespeed.co - Fri, 13 Mar 2026 13:19:15 IST - Untitled | E84: 0 | F84: 0.65
A85: 84 | B85: Carpet Couture x Bitespeed | E85: 0 | F85: 0.65
A86: 85 | B86: See Designs x Bitespeed | Trial Kickoff | E86: 0 | F86: 0.65
A87: 86 | B87: Liberty1947 x Bitespeed | E87: 0 | F87: 0.15
A88: 87 | B88: khushi@bitespeed.co - Fri, 13 Mar 2026 16:13:11 IST - Untitled | E88: 0 | F88: 0.225
A89: 88 | B89: Cococart x Bitespeed | E89: 0 | F89: 0.15
A90: 89 | B90: Oceedee x Bitespeed | C90: Oceedee | D90: oceedee.myshopify.com | E90: 1 | F90: 1
A91: 90 | B91: Chirag | E91: 0 | F91: 0.15
A92: 91 | B92: Berry Well with Life | E92: 0 | F92: 0.65
A93: 92 | B93: AI Voice Calling and Marketing Strategies | E93: 0 | F93: 0.53333333
A94: 93 | B94: Bitespeed - Books Closure for FY 2025–26 | E94: 0 | F94: 0.65
A95: 94 | B95: Walls Republic x Bitespeed | E95: 0 | F95: 0.65
A96: 95 | B96: Ether Chocolate x Bitespeed | E96: 0 | F96: 0.21428571
A97: 96 | B97: Conscious Chemist | C97: Conscious Chemist | D97: conscious-chemist.myshopify.com | E97: 1 | F97: 1
A98: 97 | B98: Presidential X Bitespeed | E98: 0 | F98: 0.44
A99: 98 | B99: Kiwi Kissan | E99: 0 | F99: 0.53333333
A100: 99 | B100: Wottagirl x Bitespeed : Connect | E100: 0 | F100: 0.21428571
A101: 100 | B101: Bitespeed - Books Closure for FY 2025–26 | E101: 0 | F101: 0.65
...

Sheet Sheet4
A1: id | B1: title
A2: 1 | B2: Rioware x Bitespeed
A3: =A2+1 -> 2 | B3: Zevar : AI Voice Review
A4: =A3+1 -> 3 | B4: Tangerine Jewelry x Bitespeed : Connect
A5: =A4+1 -> 4 | B5: Nature Fab Store
A6: =A5+1 -> 5 | B6: VIP x Bitespeed
A7: =A6+1 -> 6 | B7: hardik@bitespeed.co - Mon, 09 Mar 2026 17:12:28 IST - Untitled
A8: =A7+1 -> 7 | B8: Right4paws x Bitespeed | Trial Kickoff
A9: =A8+1 -> 8 | B9: The Clothing Factory - Discussion
A10: =A9+1 -> 9 | B10: tushita@bitespeed.co - Mon, 09 Mar 2026 17:44:13 IST - Untitled
A11: =A10+1 -> 10 | B11: Dominic Smith and navneeth | Bitespeed
A12: =A11+1 -> 11 | B12: V / Aaryaman
A13: =A12+1 -> 12 | B13: Onboarding Sync
A14: =A13+1 -> 13 | B14: L1 Sync - Knowledge + Ticket Context
... A3332: =A3331+1 -> 3331 | B3332: |B| The Floristaa <> Bitespeed

Sheet Sheet1
A1: content | B1: shopUrl | C1: group_name
A2: Hi @918697472669, sharing the meeting link here: Nutriburst <> BiteSpeed | Broadcast Friday, 18 July · 2:30 – 3:15pm Time zone: Asia/Kolkata Google Meet joining info Video call link: https://meet.google.com/rgf-eepz-ocy Or dial: ‪(US) +1 409-444-2832‬ PIN: ‪130 733 830‬# More phone numbers: https://tel.meet/rgf-eepz-ocy?pin=6197395974761 cc: @918248768964 | B2: nutriburstindia.myshopify.com | C2: Nutriburst <> Bitespeed | E2: https://meet.google.com/rgf-eepz-ocy
A3: It was shared over email. Missed sharing here! Rooted actives <> BiteSpeed Tuesday, July 15 · 5:45 – 6:00pm Time zone: Asia/Kolkata Google Meet joining info Video call link: https://meet.google.com/jcq-ykvb-zcu Or dial: ‪(US) +1 501-737-0091‬ PIN: ‪328 406 375‬# More phone numbers: https://tel.meet/jcq-ykvb-zcu?pin=6356189667126 | B3: d3ccac.myshopify.com | C3: Rooted Actives <> BiteSpeed | E3: https://meet.google.com/jcq-ykvb-zcu
A4: It was shared over email. Missed sharing here! Rooted actives <> BiteSpeed Tuesday, July 15 · 5:45 – 6:00pm Time zone: Asia/Kolkata Google Meet joining info Video call link: https://meet.google.com/jcq-ykvb-zcu Or dial: ‪(US) +1 501-737-0091‬ PIN: ‪328 406 375‬# More phone numbers: https://tel.meet/jcq-ykvb-zcu?pin=6356189667126 | B4: d3ccac.myshopify.com | C4: Rooted Actives <> BiteSpeed | E4: https://meet.google.com/jcq-ykvb-zcu
A5: Hey @917204798940 as discussed, we will be rescheduling the call to tomorrow at 1 pm, once we have access to anudeep's email. Thank you!! Gramiyaa <> Bitespeed - WA Setup + Email warmup Thursday, 17 July · 1:00 – 1:45pm Video call link: https://meet.google.com/zgw-arja-vtu | B5: gramiyaa.myshopify.com | C5: Gramiyaa <> BiteSpeed | E5: https://meet.google.com/zgw-arja-vtu
A6: Tramontina <> BiteSpeed | Marketing DB Wednesday, July 16 · 1:00 – 1:30pm Time zone: Asia/Kolkata Google Meet joining info Video call link: https://meet.google.com/pih-nqdg-gtj Or dial: ‪(US) +1 319-435-9094‬ PIN: ‪917 361 229‬# More phone numbers: https://tel.meet/pih-nqdg-gtj?pin=1307645430481 | B6: tramontina-dubai.myshopify.com | C6: Tramontina <> BiteSpeed | E6: https://meet.google.com/pih-nqdg-gtj
A7: Tramontina <> BiteSpeed | Marketing DB Wednesday, July 16 · 1:00 – 1:30pm Time zone: Asia/Kolkata Google Meet joining info Video call link: https://meet.google.com/pih-nqdg-gtj Or dial: ‪(US) +1 319-435-9094‬ PIN: ‪917 361 229‬# More phone numbers: https://tel.meet/pih-nqdg-gtj?pin=1307645430481 | B7: tramontina-dubai.myshopify.com | C7: Tramontina <> BiteSpeed | E7: https://meet.google.com/pih-nqdg-gtj
A8: Hey @917204798940 as discussed, sharing the meeting link the meeting today: Gramiyaa <> Bitespeed - WA Setup + Email warmup Wednesday, 16 July · 3:30 – 4:30pm Video call link: https://meet.google.com/zgw-arja-vtu | B8: gramiyaa.myshopify.com | C8: Gramiyaa <> BiteSpeed | E8: https://meet.google.com/zgw-arja-vtu
A9: Shvetah <> BiteSpeed Monday, July 21 · 3:00 – 3:30pm Time zone: Asia/Kolkata Google Meet joining info Video call link: https://meet.google.com/qtd-ngde-awm Or dial: ‪(US) +1 219-401-0127‬ PIN: ‪903 098 292‬# More phone numbers: https://tel.meet/qtd-ngde-awm?pin=7240875804526 | B9: bf747e-3.myshopify.com | C9: Shvetah <> BiteSpeed | E9: https://meet.google.com/qtd-ngde-awm
A10: GuitarBro <> Bitespeed Wednesday, 16 July · 1:00 – 1:15pm Time zone: Asia/Kolkata Google Meet joining info Video call link: https://meet.google.com/vcm-tzqd-xff Or dial: ‪(US) +1 651-505-3968‬ PIN: ‪938 589 261‬# More phone numbers: https://tel.meet/vcm-tzqd-xff?pin=2856362213670 | B10: playguitarbro.myshopify.com | C10: Guitarbro <> BiteSpeed | E10: https://meet.google.com/vcm-tzqd-xff
A11: Sure, can we connect at 1:15 tomorrow please? Enem Products<>Bitespeed Wednesday, 16 July · 1:15 – 2:00pm Time zone: Asia/Kolkata Google Meet joining info Video call link: https://meet.google.com/sem-zozj-ykg Or dial: ‪(US) +1 347-966-3679‬ PIN: ‪608 364 014‬# More phone numbers: https://tel.meet/sem-zozj-ykg?pin=1388162406898 | B11: 3a2931-ce.myshopify.com | C11: Enem Products <> BiteSpeed | E11: https://meet.google.com/sem-zozj-ykg
A12: Sure, can we connect at 1:15 tomorrow please? Enem Products<>Bitespeed Wednesday, 16 July · 1:15 – 2:00pm Time zone: Asia/Kolkata Google Meet joining info Video call link: https://meet.google.com/sem-zozj-ykg Or dial: ‪(US) +1 347-966-3679‬ PIN: ‪608 364 014‬# More phone numbers: https://tel.meet/sem-zozj-ykg?pin=1388162406898 | B12: 3a2931-ce.myshopify.com | C12: Enem Products <> BiteSpeed | E12: https://meet.google.com/sem-zozj-ykg
A13: Arts of Devotion <> BiteSpeed Wednesday, July 16 · 10:30 – 11:00am Time zone: Asia/Kolkata Google Meet joining info Video call link: https://meet.google.com/oxp-udbi-qbk Or dial: ‪(US) +1 315-710-5023‬ PIN: ‪778 828 590‬# More phone numbers: https://tel.meet/oxp-udbi-qbk?pin=9117508488110 | B13: 8bbdfe-51.myshopify.com | C13: Arts of Devotion <> BiteSpeed | E13: https://meet.google.com/oxp-udbi-qbk
... A71: Guitar bro<>Bitespeed Thursday, 17 July · 2:30 – 3:00pm Time zone: Asia/Kolkata Google Meet joining info Video call link: https://meet.google.com/rsi-cmze-bde Or dial: ‪(US) +1 484-909-0092‬ PIN: ‪721 752 661‬# More phone numbers: https://tel.meet/rsi-cmze-bde?pin=8971518482010 @918602723031 | B71: playguitarbro.myshopify.com | C71: Guitarbro <> BiteSpeed | E71: https://meet.google.com/rsi-cmze-bde
A72: Hey @5213333912003 good morning!! Wanted to share a quick reminder for our call today. Looking forward to meeting you: Atletica <> Bitespeed - Broadcast + CSDB Thursday, 17 Jul · 11:00 – 12:00 PM UK time Video call link: https://meet.google.com/kxs-msgo-vnf | C72: Atletica <> BiteSpeed | E72: https://meet.google.com/kxs-msgo-vnf
A73: Hey @5213333912003 good morning!! Wanted to share a quick reminder for our call today. Looking forward to meeting you: Atletica <> Bitespeed - Broadcast + CSDB Thursday, 17 Jul · 11:00 – 12:00 PM UK time Video call link: https://meet.google.com/kxs-msgo-vnf | C73: Atletica <> BiteSpeed | E73: https://meet.google.com/kxs-msgo-vnf
A74: Hi @919967899900, sharing the meeting link here: Shakehands <> BiteSpeed Friday, 18 July · 4:00 – 4:45pm Time zone: Asia/Kolkata Google Meet joining info Video call link: https://meet.google.com/gir-jaav-akt Or dial: ‪(US) +1 321-586-0994‬ PIN: ‪678 431 388‬# More phone numbers: https://tel.meet/gir-jaav-akt?pin=2942895319272 | B74: shake-hands-f51f.myshopify.com | C74: Shakehands <> BiteSpeed | E74: https://meet.google.com/gir-jaav-akt
A75: Gemstone Galaxy <> Bitespeed - Catalog Friday, 18 July · 4:30 – 5:00pm Time zone: Asia/Kolkata Google Meet joining info Video call link: https://meet.google.com/sqt-amvk-xkp Or dial: ‪(US) +1 267-755-7916‬ PIN: ‪811 759 439‬# More phone numbers: https://tel.meet/sqt-amvk-xkp?pin=2718540047363 | B75: 60e3c1-3.myshopify.com | C75: Gemstone Galaxy <> BiteSpeed | E75: https://meet.google.com/sqt-amvk-xkp
A76: Paaduks <> BiteSpeed | Broadcast Friday, July 18 · 12:00 – 12:30pm Time zone: Asia/Kolkata Google Meet joining info Video call link: https://meet.google.com/emr-ywmx-izg Or dial: ‪(US) +1 929-266-1944‬ PIN: ‪291 123 046‬# More phone numbers: https://tel.meet/emr-ywmx-izg?pin=9336685364245 | B76: paaduks.myshopify.com | C76: Paaduks <> BiteSpeed | E76: https://meet.google.com/emr-ywmx-izg
A77: Paaduks <> BiteSpeed | Broadcast Friday, July 18 · 12:00 – 12:30pm Time zone: Asia/Kolkata Google Meet joining info Video call link: https://meet.google.com/emr-ywmx-izg Or dial: ‪(US) +1 929-266-1944‬ PIN: ‪291 123 046‬# More phone numbers: https://tel.meet/emr-ywmx-izg?pin=9336685364245 | B77: paaduks.myshopify.com | C77: Paaduks <> BiteSpeed | E77: https://meet.google.com/emr-ywmx-izg
A78: Moarmouz <> BiteSpeed | Support DB Friday, July 18 · 2:30 – 3:00pm Time zone: Asia/Kolkata Google Meet joining info Video call link: https://meet.google.com/ndc-nyjs-gfg Or dial: ‪(US) +1 515-605-0189‬ PIN: ‪831 564 805‬# More phone numbers: https://tel.meet/ndc-nyjs-gfg?pin=4366170774048 cc: @918548083112 | B78: molifestyle-3.myshopify.com | C78: Moarmouz <> BiteSpeed | E78: https://meet.google.com/ndc-nyjs-gfg
A79: Moarmouz <> BiteSpeed | Support DB Friday, July 18 · 2:30 – 3:00pm Time zone: Asia/Kolkata Google Meet joining info Video call link: https://meet.google.com/ndc-nyjs-gfg Or dial: ‪(US) +1 515-605-0189‬ PIN: ‪831 564 805‬# More phone numbers: https://tel.meet/ndc-nyjs-gfg?pin=4366170774048 cc: @918548083112 | B79: molifestyle-3.myshopify.com | C79: Moarmouz <> BiteSpeed | E79: https://meet.google.com/ndc-nyjs-gfg
A80: Rooted Actives <> BiteSpeed Friday, July 18 · 3:30 – 4:00pm Time zone: Asia/Kolkata Google Meet joining info Video call link: https://meet.google.com/nyb-ehfv-gdj Or dial: ‪(US) +1 904-900-0084‬ PIN: ‪458 846 361‬# More phone numbers: https://tel.meet/nyb-ehfv-gdj?pin=6898609802055 | B80: d3ccac.myshopify.com | C80: Rooted Actives <> BiteSpeed | E80: https://meet.google.com/nyb-ehfv-gdj
A81: Sure thing @919972555719 Here's the invite Senses India<>Bitespeed Monday, 21 Jul • 12:30 – 1:00 pm Google Meet joining info Video call link: https://meet.google.com/qra-fmxc-ogg Or dial: +1 563-503-5267 PIN: 420 112 710# More phone numbers: https://tel.meet/qra-fmxc-ogg?pin=9432491675929 | B81: senses-india.myshopify.com | C81: Senses India <> BiteSpeed | E81: https://meet.google.com/qra-fmxc-ogg
A82: Sure thing @919972555719 Here's the invite Senses India<>Bitespeed Monday, 21 Jul • 12:30 – 1:00 pm Google Meet joining info Video call link: https://meet.google.com/qra-fmxc-ogg Or dial: +1 563-503-5267 PIN: 420 112 710# More phone numbers: https://tel.meet/qra-fmxc-ogg?pin=9432491675929 | B82: senses-india.myshopify.com | C82: Senses India <> BiteSpeed | E82: https://meet.google.com/qra-fmxc-ogg
A83: Hi @917310699509, sharing the meeting link here: Terrana <> BiteSpeed | Onboarding Tuesday, 22 July · 1:00 – 1:45pm Time zone: Asia/Kolkata Google Meet joining info Video call link: https://meet.google.com/fpg-tbjp-sbs Or dial: ‪(US) +1 650-667-0390‬ PIN: ‪620 770 482‬# More phone numbers: https://tel.meet/fpg-tbjp-sbs?pin=7858277778015 | B83: df40ba-60.myshopify.com | C83: Terrana <> BiteSpeed | E83: https://meet.google.com/fpg-tbjp-sbs
A84: The Good Doll <> BiteSpeed | Support Dashboard Walkthrough Monday, 21 July · 4:00 – 4:30pm Video call link: https://meet.google.com/rfs-uyyn-ods | B84: theshopgoodgift.myshopify.com | C84: The Good Doll <> BiteSpeed | E84: https://meet.google.com/rfs-uyyn-ods
A85: Hey @447866223399 good morning!! I have joined the meeting link scheduled for us. Sharing the link below for your reference: Car Cologne <> Bitespeed - Broadcasts review Monday, 21 July · 4:00 – 5:00pm Video call link: https://meet.google.com/eau-czbc-xog | B85: carcalogne.myshopify.com | C85: Car Cologne <> BiteSpeed | E85: https://meet.google.com/eau-czbc-xog
... A218: Hi @918450955942, sharing the meeting link here: Svarn Jewels <> BiteSpeed | Broadcast Friday, 25 July · 5:00 – 5:45pm Time zone: Asia/Kolkata Google Meet joining info Video call link: https://meet.google.com/egh-xisf-ncu Or dial: ‪(US) +1 682-727-0375‬ PIN: ‪242 799 623‬# More phone numbers: https://tel.meet/egh-xisf-ncu?pin=6272036858570 | B218: b0db2e-04.myshopify.com | C218: Svarn Jewels <> Bitespeed | E218: https://meet.google.com/egh-xisf-ncu
A219: meet.google.com/zsa-igus-vna | B219: 3a2931-ce.myshopify.com | C219: Enem Products <> BiteSpeed | E219: #N/A
A220: https://meet.google.com/fzf-jext-bkd | B220: bummer-in.myshopify.com | C220: Bummer <> Bitespeed | E220: https://meet.google.com/fzf-jext-bkd
A221: Dring <> BiteSpeed Wednesday, 30 July · 5:30 – 6:15pm Video call link: https://meet.google.com/ene-bnxx-chf | B221: dring-india.myshopify.com | C221: Dring <> BiteSpeed | E221: https://meet.google.com/ene-bnxx-chf
A222: Wednesday, 30 July · 3:30 – 4:00pm Video call link: https://meet.google.com/waj-rsts-kpw | B222: minimal-mate.myshopify.com | C222: Everlasting <> BiteSpeed | E222: https://meet.google.com/waj-rsts-kpw
A223: Hey @916283528519, gentle reminder for our call Banno Swagger <> BiteSpeed Wednesday, 30 July · 3:00 – 3:30pm Video call link: https://meet.google.com/mei-fivi-cct | B223: bannosswagger.myshopify.com | C223: Banno Swagger <> BiteSpeed | E223: https://meet.google.com/mei-fivi-cct
A224: UNO Aroma <> BiteSpeed Saturday, 26 July · 10:30 – 11:00am Video call link: https://meet.google.com/tsb-zrrw-svr I'm on the call @917201888080 | B224: unoaroma-store.myshopify.com | C224: UNO Aroma <> BiteSpeed | E224: https://meet.google.com/tsb-zrrw-svr
A225: Hi @919970385173 as discussed on call, sharing the meeting link here: Krazy Caterpillar <> BiteSpeed Saturday 26 Jul · 10:30 – 11 AM Google Meet joining info Video call link: https://meet.google.com/qdw-fkqv-uzc Or dial: +1 385-645-7920 PIN: 474322636 More phone numbers: https://tel.meet/qdw-fkqv-uzc?pin=8413607093954 cc: @918309108052 | B225: krazy-caterpillar.myshopify.com | C225: Krazy Caterpillar <> BiteSpeed | E225: https://meet.google.com/qdw-fkqv-uzc
A226: Hi @918450955942 as discussed, sharing the meeting link here: Svarn Jewels <> BiteSpeed | Broadcast Saturday 26 Jul · 1 – 1:45 PM Google Meet joining info Video call link: https://meet.google.com/pku-xiuh-nqj Or dial: +1 929-266-1085 PIN: 361481623 More phone numbers: https://tel.meet/pku-xiuh-nqj?pin=5149125478767 | B226: b0db2e-04.myshopify.com | C226: Svarn Jewels <> Bitespeed | E226: https://meet.google.com/pku-xiuh-nqj
A227: Hi @919970385173 Thank you for connecting. As per our discussion, I have scheduled a 30-minute slot for the Tirla discussion tomorrow at 5 PM. Krazy Caterpillar <> BiteSpeed: Trial Discussion Monday, 28 July · 5:00 – 5:30pm Time zone: Asia/Kolkata Google Meet joining info Video call link: https://meet.google.com/rwv-gbyy-ykb cc @917827174101 @919650721486 Or dial: ‪(US) +1 240-903-4182‬ PIN: ‪294 667 511‬# More phone numbers: https://tel.meet/rwv-gbyy-ykb?pin=4728618939277 | B227: krazy-caterpillar.myshopify.com | C227: Krazy Caterpillar <> BiteSpeed | E227: https://meet.google.com/rwv-gbyy-ykb
A228: N4N <> BiteSpeed | Primary no. set up Monday, July 28 · 12:30 – 1:00pm Time zone: Asia/Kolkata Google Meet joining info Video call link: https://meet.google.com/qzo-xonf-sep Or dial: ‪(US) +1 470-228-6480‬ PIN: ‪194 195 746‬# More phone numbers: https://tel.meet/qzo-xonf-sep?pin=1002516926741 | B228: f18267-e3.myshopify.com | C228: Nature4Nature <> BiteSpeed | E228: https://meet.google.com/qzo-xonf-sep
A229: Soothi Syahi <> Bitespeed - Resume onboarding Monday, July 28 · 12:00 – 12:30pm Time zone: Asia/Kolkata Google Meet joining info Video call link: https://meet.google.com/djr-hpda-yqg Or dial: ‪(US) +1 442-900-4351‬ PIN: ‪767 490 454‬# More phone numbers: https://tel.meet/djr-hpda-yqg?pin=9229096644546 | B229: sootisyahi.myshopify.com | C229: Sooti Syahi <> BiteSpeed | E229: https://meet.google.com/djr-hpda-yqg
A230: Paaduks <> BiteSpeed Monday, July 28 · 5:45 – 6:15pm Time zone: Asia/Kolkata Google Meet joining info Video call link: https://meet.google.com/qfw-jtei-bgq Or dial: ‪(US) +1 856-687-3098‬ PIN: ‪483 271 225‬# More phone numbers: https://tel.meet/qfw-jtei-bgq?pin=4769942385854 | B230: paaduks.myshopify.com | C230: Paaduks <> BiteSpeed | E230: https://meet.google.com/qfw-jtei-bgq
A231: @916264976610 Invite for our call today! Paaduks <> BiteSpeed Monday, July 28 · 5:45 – 6:15pm Time zone: Asia/Kolkata Google Meet joining info Video call link: https://meet.google.com/qfw-jtei-bgq Or dial: ‪(US) +1 856-687-3098‬ PIN: ‪483 271 225‬# More phone numbers: https://tel.meet/qfw-jtei-bgq?pin=4769942385854 | B231: paaduks.myshopify.com | C231: Paaduks <> BiteSpeed | E231: https://meet.google.com/qfw-jtei-bgq
... A307: Hey @919662131825 Sockscarving <> BiteSpeed Weekly Connect Wednesday, 6 August · 3:00 – 3:30pm Video call link: https://meet.google.com/feg-dboc-bgq | B307: f60f9f.myshopify.com | C307: Sockscarving <> BiteSpeed | E307: https://meet.google.com/feg-dboc-bgq
A308: meet.google.com/btg-ywmv-hco | B308: 32c32b-cb.myshopify.com | C308: Carlton Beauty London | E308: #N/A
A309: Zaudi Luxe <> BiteSpeed Broadcast and Optin Setup Wednesday, 6 August · 5:30 – 6:00pm Video call link: https://meet.google.com/zkv-dffm-nak | B309: 0222b5-d2.myshopify.com | C309: Zaudi Luxe <> Bitespeed | E309: https://meet.google.com/zkv-dffm-nak
A310: Hi @919656301234, sharing the meeting link here: Cradiac <> BiteSpeed | Support dashboard Tuesday, 12 August · 5:00 – 5:45pm Time zone: Asia/Kolkata Google Meet joining info Video call link: https://meet.google.com/jqc-ewnd-siz Or dial: ‪(US) +1 414-909-7120‬ PIN: ‪982 895 175‬# More phone numbers: https://tel.meet/jqc-ewnd-siz?pin=6123312886498 | B310: lilfoot-kids.myshopify.com | C310: Cradiac | E310: https://meet.google.com/jqc-ewnd-siz
A311: Curl Up <> BiteSpeed | Review call Tuesday, August 12 · 4:30 – 5:00pm Time zone: Asia/Kolkata Google Meet joining info Video call link: https://meet.google.com/sqi-vugp-pke Or dial: ‪(US) +1 470-268-2229‬ PIN: ‪180 784 369‬# More phone numbers: https://tel.meet/sqi-vugp-pke?pin=4096758185156 | B311: curlupp.myshopify.com | C311: Curl Up | E311: https://meet.google.com/sqi-vugp-pke
A312: Hi @918956123060, sharing the meeting link here: Agri-Route <> BiteSpeed Tuesday, 12 August · 4:00 – 4:45pm Time zone: Asia/Kolkata Google Meet joining info Video call link: https://meet.google.com/sbr-ujdp-gqp Or dial: ‪(US) +1 385-352-0908‬ PIN: ‪816 388 917‬# More phone numbers: https://tel.meet/sbr-ujdp-gqp?pin=1659157219141 | B312: agri-route.myshopify.com | C312: Agri-route | E312: https://meet.google.com/sbr-ujdp-gqp
A313: Rasoi Shop<>Bitespeed Tuesday, 12 August · 3:45 – 4:15pm Time zone: Asia/Kolkata Google Meet joining info Video call link: https://meet.google.com/ikd-rrup-rtx Or dial: ‪(US) +1 440-462-3434‬ PIN: ‪332 576 995‬# More phone numbers: https://tel.meet/ikd-rrup-rtx?pin=6777788071230 @918758870917 lemme know whenever you join, on the call! | B313: rasoi-shop.myshopify.com | C313: Rasoi Shop <> BiteSpeed | E313: https://meet.google.com/ikd-rrup-rtx
A314: Rasoi Shop<>Bitespeed Tuesday, 12 August · 3:45 – 4:15pm Time zone: Asia/Kolkata Google Meet joining info Video call link: https://meet.google.com/ikd-rrup-rtx Or dial: ‪(US) +1 440-462-3434‬ PIN: ‪332 576 995‬# More phone numbers: https://tel.meet/ikd-rrup-rtx?pin=6777788071230 @918758870917 lemme know whenever you join, on the call! | B314: rasoi-shop.myshopify.com | C314: Rasoi Shop <> BiteSpeed | E314: https://meet.google.com/ikd-rrup-rtx
A315: Also sharing the link for tomorrow's weekly meeting, The Tan Clan <> BiteSpeed: Weekly Connect Wednesday, 13 August · 5:00 – 5:45pm Video call link: https://meet.google.com/wcc-ktgo-nji | B315: the-tan-clan.myshopify.com | C315: The Tan Clan <> BiteSpeed | E315: https://meet.google.com/wcc-ktgo-nji
A316: I'm on the call https://meet.google.com/zmd-axzt-rbs?authuser=0 | B316: emperor-akbar-cardamom.myshopify.com | C316: Emperorakbar | E316: https://meet.google.com/zmd-axzt-rbs
A317: Also @918898767231 Here is the link for meeting with your social media team. You can add them to our group too Dr. Vaidya<>Bitespeed (IG Automation) Tuesday, 12 August · 2:15 – 3:00pm Time zone: Asia/Kolkata Google Meet joining info Video call link: https://meet.google.com/zho-mkgd-fai Or dial: ‪(US) +1 413-889-0304‬ PIN: ‪258 814 421‬# More phone numbers: https://tel.meet/zho-mkgd-fai?pin=6557698822768 | B317: dr-vaidya.myshopify.com | C317: Dr. Vaidya's <> BiteSpeed | E317: https://meet.google.com/zho-mkgd-fai
A318: Here is the invite for tomorrow Dr. Vaidya<>Bitespeed (IG Automation) Wednesday, 13 August · 3:00 – 3:45pm Time zone: Asia/Kolkata Google Meet joining info Video call link: https://meet.google.com/zho-mkgd-fai Or dial: ‪(US) +1 413-889-0304‬ PIN: ‪258 814 421‬# More phone numbers: https://tel.meet/zho-mkgd-fai?pin=6557698822768 | B318: dr-vaidya.myshopify.com | C318: Dr. Vaidya's <> BiteSpeed | E318: https://meet.google.com/zho-mkgd-fai
A319: @919625145765 We can join the below link Trade UNO Catalogue Integration Tuesday, 12 August · 2:30 – 3:00pm Time zone: Asia/Kolkata Google Meet joining info Video call link: https://meet.google.com/ydm-zaoe-gff Or dial: ‪(US) +1 252-713-7128‬ PIN: ‪507 766 185‬# More phone numbers: https://tel.meet/ydm-zaoe-gff?pin=3265840211281 | B319: trade-uno.myshopify.com | C319: Trade UNO | E319: https://meet.google.com/ydm-zaoe-gff
A320: Here’s the link Guitarbro<>Bitespeed Tuesday, 12 August · 7:00 – 7:30pm Time zone: Asia/Kolkata Google Meet joining info Video call link: https://meet.google.com/ata-qdpm-hib Or dial: ‪(US) +1 585-491-8785‬ PIN: ‪755 605 442‬# More phone numbers: https://tel.meet/ata-qdpm-hib?pin=9669369732011 | B320: playguitarbro.myshopify.com | C320: Guitarbro <> BiteSpeed | E320: https://meet.google.com/ata-qdpm-hib
A321: Here is the invite for our meeting at 4 Blue Island<>Bitespeed Wednesday, 13 August · 4:00 – 4:45pm Time zone: Asia/Kolkata Google Meet joining info Video call link: https://meet.google.com/ucg-hpcy-orr Or dial: ‪(US) +1 307-364-0831‬ PIN: ‪685 865 910‬# More phone numbers: https://tel.meet/ucg-hpcy-orr?pin=4911961642237 | B321: stain-proof-shirt.myshopify.com | C321: Blue Island | E321: https://meet.google.com/ucg-hpcy-orr
A322: Hi team, here's the link for our call at 5:30 meet.google.com/paw-tbug-xgz | B322: amwoodo-live.myshopify.com | C322: Ecoconsious | E322: #N/A
A323: @919302873075 We Spoke RAS Luxury<>Bitespeed Monday, 18 August · 3:00 – 3:30pm Time zone: Asia/Kolkata Google Meet joining info Video call link: https://meet.google.com/ehp-yxph-qmg Or dial: ‪(US) +1 401-426-4875‬ PIN: ‪217 056 749‬# More phone numbers: https://tel.meet/ehp-yxph-qmg?pin=9235976124550 | B323: ras-luxury-oils-india.myshopify.com | C323: RAS luxury Oils | E323: https://meet.google.com/ehp-yxph-qmg
A324: Here is the invite Krafted Millets<>Bitespeed Wednesday, 13 August · 6:30 – 7:00pm Time zone: Asia/Kolkata Google Meet joining info Video call link: https://meet.google.com/yvr-eovn-vic Or dial: ‪(US) +1 505-585-5203‬ PIN: ‪325 109 674‬# More phone numbers: https://tel.meet/yvr-eovn-vic?pin=7069268701553 | B324: 6fd21b-76.myshopify.com | C324: Krafted Millets | E324: https://meet.google.com/yvr-eovn-vic
A325: Thanks for confirming, I have sent an invite for 9 am mexico time, looking forward to connecting today: Atletica <> Bitespeed - Trail review Wednesday, 13 August · 9:00 – 9:45 am Mexico time Video call link: https://meet.google.com/tkp-vdwo-drf | C325: Atletica <> BiteSpeed | E325: https://meet.google.com/tkp-vdwo-drf
A326: Video call link: https://meet.google.com/xsm-qpso-kqi | B326: d2c01e-32.myshopify.com | C326: Digi Hub | E326: https://meet.google.com/xsm-qpso-kqi
A327: Sharing link for your reference. Casebasket Tuesday, 12 August · 7:15 – 7:30pm Time zone: Asia/Kolkata Google Meet joining info Video call link: https://meet.google.com/mhm-qhaa-exd Or dial: ‪(US) +1 567-316-0917‬ PIN: ‪339 059 405‬# More phone numbers: https://tel.meet/mhm-qhaa-exd?pin=1148878925491 | B327: 301cbc-58.myshopify.com | C327: Casebasket | E327: https://meet.google.com/mhm-qhaa-exd
A328: Bitamin <> BiteSpeed | Support, CG, Broadcast Wednesday, August 13 · 5:00 – 5:45pm Time zone: Asia/Kolkata Google Meet joining info Video call link: https://meet.google.com/mha-fqcz-frk Or dial: ‪(US) +1 419-901-8891‬ PIN: ‪250 694 300‬# More phone numbers: https://tel.meet/mha-fqcz-frk?pin=8171843265048 | B328: b7abe7-2.myshopify.com | C328: Bitamin | E328: https://meet.google.com/mha-fqcz-frk
A329: Optimum Nutrition <> BiteSpeed | Review Call Wednesday, August 13 · 11:30am – 12:00pm Time zone: Asia/Kolkata Google Meet joining info Video call link: https://meet.google.com/nhg-wgmv-cwr Or dial: ‪(US) +1 320-336-0079‬ PIN: ‪226 574 345‬# More phone numbers: https://tel.meet/nhg-wgmv-cwr?pin=6033658467986 | B329: optimumnutritionin.myshopify.com | C329: Optimum Nutrition | E329: https://meet.google.com/nhg-wgmv-cwr
A330: Carloginn <> Bitespeed - Discussion Thursday, 14 August · 3:00 – 3:30pm Time zone: Asia/Kolkata Google Meet joining info Video call link: https://meet.google.com/djx-sfum-egx Or dial: ‪(US) +1 314-666-2446‬ PIN: ‪584 079 289‬# More phone numbers: https://tel.meet/djx-sfum-egx?pin=4109260100322 @919574873073, please find the link for the meeting | B330: 6079df.myshopify.com | C330: Carloginn | E330: https://meet.google.com/djx-sfum-egx
A331: Carloginn <> Bitespeed - Discussion Thursday, 14 August · 3:00 – 3:30pm Time zone: Asia/Kolkata Google Meet joining info Video call link: https://meet.google.com/djx-sfum-egx Or dial: ‪(US) +1 314-666-2446‬ PIN: ‪584 079 289‬# More phone numbers: https://tel.meet/djx-sfum-egx?pin=4109260100322 @919574873073, please find the link for the meeting | B331: 6079df.myshopify.com | C331: Carloginn | E331: https://meet.google.com/djx-sfum-egx
A332: Serenity Jewels <> BiteSpeed | Broadcast Wednesday, 13 August · 2:00 – 2:30pm Video call link: https://meet.google.com/zes-ajbd-ewq | B332: serenity-21k.myshopify.com | C332: Serenity Jewels | E332: https://meet.google.com/zes-ajbd-ewq
A333: Dheu x Bitespeed Wednesday, 13 August · 12:00 – 12:30pm Time zone: Asia/Kolkata Google Meet joining info Video call link: https://meet.google.com/fia-padi-mtf Or dial: ‪(US) +1 262-977-4619‬ PIN: ‪353 014 382‬# More phone numbers: https://tel.meet/fia-padi-mtf?pin=7978640162536 | B333: dheu-2.myshopify.com | C333: Dheu | E333: https://meet.google.com/fia-padi-mtf
A334: Dheu x Bitespeed Wednesday, 13 August · 12:00 – 12:30pm Time zone: Asia/Kolkata Google Meet joining info Video call link: https://meet.google.com/fia-padi-mtf Or dial: ‪(US) +1 262-977-4619‬ PIN: ‪353 014 382‬# More phone numbers: https://tel.meet/fia-padi-mtf?pin=7978640162536 | B334: dheu-2.myshopify.com | C334: Dheu | E334: https://meet.google.com/fia-padi-mtf
A335: Amulyah Shop Wednesday, 13 August · 1:00 – 1:30pm Time zone: Asia/Kolkata Google Meet joining info Video call link: https://meet.google.com/qmj-wtxt-qee Or dial: ‪(US) +1 484-416-2085‬ PIN: ‪920 795 408‬# More phone numbers: https://tel.meet/qmj-wtxt-qee?pin=7792347099162 | B335: 329y6r-t0.myshopify.com | C335: Amulyah | E335: https://meet.google.com/qmj-wtxt-qee
A336: Priyangaa Wednesday, 13 August · 12:00 – 12:30pm Time zone: Asia/Kolkata Google Meet joining info Video call link: https://meet.google.com/cjv-insf-cwe Or dial: ‪(US) +1 484-424-6721‬ PIN: ‪312 828 004‬# More phone numbers: https://tel.meet/cjv-insf-cwe?pin=9889366625657 | B336: priyangaa-sarees.myshopify.com | C336: Priyangaa <> BiteSpeed | E336: https://meet.google.com/cjv-insf-cwe
A337: Sharing the link for your reference. Casebasket Wednesday, 13 August · 4:00 – 4:30pm Time zone: Asia/Kolkata Google Meet joining info Video call link: https://meet.google.com/vsv-tkcw-wkt Or dial: ‪(US) +1 904-580-9652‬ PIN: ‪702 041 830‬# More phone numbers: https://tel.meet/vsv-tkcw-wkt?pin=6181440255060 | B337: 301cbc-58.myshopify.com | C337: Casebasket | E337: https://meet.google.com/vsv-tkcw-wkt
... A411: More Pen <> BiteSpeed: Way Forward Tuesday, 19 August · 11:00 – 11:45am Video call link: https://meet.google.com/jwq-jqnd-xvc | B411: dr-morpen.myshopify.com | C411: More Pen <> BiteSpeed | E411: https://meet.google.com/jwq-jqnd-xvc
A412: Hi @919316734827 as discussed over call, sharing the meeting link here: Zjoolry <> BiteSpeed || Trial kickoff! Tuesday, 19 August · 10:00 – 10:45am Time zone: Asia/Kolkata Google Meet joining info Video call link: https://meet.google.com/dtx-qixh-rkd Or dial: ‪(US) +1 614-948-6211‬ PIN: ‪757 817 200‬# More phone numbers: https://tel.meet/dtx-qixh-rkd?pin=1185343154021 | C412: Zjoolry <> BiteSpeed | E412: https://meet.google.com/dtx-qixh-rkd
A413: Flirtatious - +91 Number onboarding Monday, 18 August · 1:00 – 1:45pm Time zone: Asia/Kolkata Google Meet joining info Video call link: https://meet.google.com/mug-iyoq-spb Or dial: ‪(US) +1 615-787-8589‬ PIN: ‪702 704 734‬# More phone numbers: https://tel.meet/mug-iyoq-spb?pin=5894051666045 @918266033551 | B413: flirtatious-in.myshopify.com | C413: Flirtatious<> BiteSpeed | E413: https://meet.google.com/mug-iyoq-spb
A414: Flirtatious - +91 Number onboarding Monday, 18 August · 1:00 – 1:45pm Time zone: Asia/Kolkata Google Meet joining info Video call link: https://meet.google.com/mug-iyoq-spb Or dial: ‪(US) +1 615-787-8589‬ PIN: ‪702 704 734‬# More phone numbers: https://tel.meet/mug-iyoq-spb?pin=5894051666045 @918266033551 | B414: flirtatious-in.myshopify.com | C414: Flirtatious<> BiteSpeed | E414: https://meet.google.com/mug-iyoq-spb
A415: Carloginn <> Bitespeed - Discussion Tuesday, 19 August · 5:30 – 6:15pm Time zone: Asia/Kolkata Google Meet joining info Video call link: https://meet.google.com/fsf-mipd-xxy Or dial: ‪(US) +1 774-314-4100‬ PIN: ‪696 665 249‬# More phone numbers: https://tel.meet/fsf-mipd-xxy?pin=7032340688808 @919574873073 | B415: 6079df.myshopify.com | C415: Carloginn | E415: https://meet.google.com/fsf-mipd-xxy
A416: Hi @917042355568 @918850254612, sharing the meeting link here: Effectinn Lingerie <> BiteSpeed Tuesday, 19 August · 2:30 – 3:15pm Time zone: Asia/Kolkata Google Meet joining info Video call link: https://meet.google.com/ors-fack-jxf Or dial: ‪(US) +1 216-930-9181‬ PIN: ‪936 958 964‬# More phone numbers: https://tel.meet/ors-fack-jxf?pin=8662679182478 | B416: effectinn.myshopify.com | C416: Effectinn Lingerie | E416: https://meet.google.com/ors-fack-jxf
A417: Carloginn <> Bitespeed - Discussion Tuesday, 19 August · 5:30 – 6:15pm Time zone: Asia/Kolkata Google Meet joining info Video call link: https://meet.google.com/fsf-mipd-xxy Or dial: ‪(US) +1 774-314-4100‬ PIN: ‪696 665 249‬# More phone numbers: https://tel.meet/fsf-mipd-xxy?pin=7032340688808 @919574873073 | B417: 6079df.myshopify.com | C417: Carloginn | E417: https://meet.google.com/fsf-mipd-xxy
A418: Thanks for your time on the call @918697472669. Below is the meet link for tomorrow. NutriBurst <> Bitespeed: Migration Call Wednesday, 20 August · 10:30 – 11:00am Time zone: Asia/Kolkata Google Meet joining info Video call link: https://meet.google.com/yew-vxff-dmo Or dial: ‪(US) +1 504-941-9705‬ PIN: ‪206 056 192‬# More phone numbers: https://tel.meet/yew-vxff-dmo?pin=1728762888018 | B418: nutriburstindia.myshopify.com | C418: Nutriburst <> Bitespeed | E418: https://meet.google.com/yew-vxff-dmo
A419: Serenity Jewels <> BiteSpeed Tuesday, 19 August · 2:30 – 3:00pm Video call link: https://meet.google.com/zes-ajbd-ewq | B419: serenity-21k.myshopify.com | C419: Serenity Jewels | E419: https://meet.google.com/zes-ajbd-ewq
A420: Hey @919820044077, As discussed last week, lets connect today so I can address all the queries and you can have understanding of both the dashboards. Shop Football <> BiteSpeed | Review Tuesday, August 19 · 12:00 – 12:30pm Time zone: Asia/Kolkata Google Meet joining info Video call link: https://meet.google.com/rkt-wjcy-ixb Or dial: ‪(US) +1 321-586-0645‬ PIN: ‪209 144 579‬# More phone numbers: https://tel.meet/rkt-wjcy-ixb?pin=3932267558450 | B420: 3b0520-2.myshopify.com | C420: Shopfootball | E420: https://meet.google.com/rkt-wjcy-ixb
A421: Nanditabist <> BiteSpeed | Support DB Monday, August 18 · 12:00 – 12:30pm Time zone: Asia/Kolkata Google Meet joining info Video call link: https://meet.google.com/ryr-dkio-drj Or dial: ‪(US) +1 219-767-0250‬ PIN: ‪819 480 665‬# More phone numbers: https://tel.meet/ryr-dkio-drj?pin=7098828601261 | B421: craze-by.myshopify.com | C421: Vibecrafts | E421: https://meet.google.com/ryr-dkio-drj
A422: Curl Up <> BiteSpeed | Support and Trial ending discussion Monday, August 18 · 3:00 – 3:45pm Time zone: Asia/Kolkata Google Meet joining info Video call link: https://meet.google.com/toi-ssoq-bpg Or dial: ‪(US) +1 413-370-4161‬ PIN: ‪803 385 664‬# More phone numbers: https://tel.meet/toi-ssoq-bpg?pin=3453488360322 | B422: curlupp.myshopify.com | C422: Curl Up | E422: https://meet.google.com/toi-ssoq-bpg
A423: Me and My <> BiteSpeed | WA set up Monday, August 18 · 6:15 – 6:45pm Time zone: Asia/Kolkata Google Meet joining info Video call link: https://meet.google.com/eub-sowx-cbi Or dial: ‪(US) +1 862-205-3248‬ PIN: ‪479 720 100‬# More phone numbers: https://tel.meet/eub-sowx-cbi?pin=2021404601435 | B423: 802b4d-2.myshopify.com | C423: Me & My | E423: https://meet.google.com/eub-sowx-cbi
A424: @917032377769 Invite for our call today! Bitamin <> BiteSpeed | Support DB Monday, August 18 · 5:00 – 5:30pm Time zone: Asia/Kolkata Google Meet joining info Video call link: https://meet.google.com/vts-cwrp-via Or dial: ‪(US) +1 864-657-0563‬ PIN: ‪429 076 674‬# More phone numbers: https://tel.meet/vts-cwrp-via?pin=2566897354548 | B424: b7abe7-2.myshopify.com | C424: Bitamin | E424: https://meet.google.com/vts-cwrp-via
... A433: Vidobi <> BiteSpeed | AI flows, Catalogue Set up and Support DB activation Friday, August 22 · 3:00 – 3:30pm Time zone: Asia/Kolkata Google Meet joining info Video call link: https://meet.google.com/wxe-gfmp-kdk Or dial: ‪(US) +1 601-516-5310‬ PIN: ‪786 330 740‬# More phone numbers: https://tel.meet/wxe-gfmp-kdk?pin=7473097269622 | B433: 8ea801-a8.myshopify.com | C433: Vedobi <> Bitespeed | E433: https://meet.google.com/wxe-gfmp-kdk
A434: Anant Exports <> Bitespeed - Discussion Friday, 22 August · 5:45 – 6:30pm Time zone: Asia/Kolkata Google Meet joining info Video call link: https://meet.google.com/icc-etjx-fic Or dial: ‪(US) +1 219-321-0690‬ PIN: ‪156 368 196‬# More phone numbers: https://tel.meet/icc-etjx-fic?pin=3958640736954 @919737779510 | C434: Anant Exports <> BiteSpeed | E434: https://meet.google.com/icc-etjx-fic
A435: Dheu <> Bitespeed - Discussion Tuesday, 19 August · 4:45 – 5:30pm Time zone: Asia/Kolkata Google Meet joining info Video call link: https://meet.google.com/weg-zbky-ggz Or dial: ‪(US) +1 864-688-9805‬ PIN: ‪929 415 446‬# More phone numbers: https://tel.meet/weg-zbky-ggz?pin=4234732411175 @919830128169, reminder for our call at 4:45pm today! | B435: dheu-2.myshopify.com | C435: Dheu | E435: https://meet.google.com/weg-zbky-ggz
A436: Dheu <> Bitespeed - Discussion Tuesday, 19 August · 4:45 – 5:30pm Time zone: Asia/Kolkata Google Meet joining info Video call link: https://meet.google.com/weg-zbky-ggz Or dial: ‪(US) +1 864-688-9805‬ PIN: ‪929 415 446‬# More phone numbers: https://tel.meet/weg-zbky-ggz?pin=4234732411175 @919830128169, reminder for our call at 4:45pm today! | B436: dheu-2.myshopify.com | C436: Dheu | E436: https://meet.google.com/weg-zbky-ggz
A437: Truth & Beauty <> Bitespeed - Webhook Addition Tuesday, 19 August · 6:00 – 6:30pm Time zone: Asia/Kolkata Google Meet joining info Video call link: https://meet.google.com/uvq-uzes-uwv Or dial: ‪(US) +1 339-674-7188‬ PIN: ‪964 844 714‬# More phone numbers: https://tel.meet/uvq-uzes-uwv?pin=6511702746590 @917737853411, please find the link for the meeting | B437: 72be34-df.myshopify.com | C437: Truth & Beauty | E437: https://meet.google.com/uvq-uzes-uwv
A438: Truth & Beauty <> Bitespeed - Webhook Addition Tuesday, 19 August · 6:00 – 6:30pm Time zone: Asia/Kolkata Google Meet joining info Video call link: https://meet.google.com/uvq-uzes-uwv Or dial: ‪(US) +1 339-674-7188‬ PIN: ‪964 844 714‬# More phone numbers: https://tel.meet/uvq-uzes-uwv?pin=6511702746590 @917737853411, please find the link for the meeting | B438: 72be34-df.myshopify.com | C438: Truth & Beauty | E438: https://meet.google.com/uvq-uzes-uwv
A439: Hi @919830128169, we spoke, as discussed, we shall have the meeting at 9pm today Dheu <> Bitespeed - Discussion Tuesday, 19 August · 9:00 – 9:45pm Time zone: Asia/Kolkata Google Meet joining info Video call link: https://meet.google.com/weg-zbky-ggz Or dial: ‪(US) +1 864-688-9805‬ PIN: ‪929 415 446‬# More phone numbers: https://tel.meet/weg-zbky-ggz?pin=4234732411175 | B439: dheu-2.myshopify.com | C439: Dheu | E439: https://meet.google.com/weg-zbky-ggz
A440: Hi @919830128169, we spoke, as discussed, we shall have the meeting at 9pm today Dheu <> Bitespeed - Discussion Tuesday, 19 August · 9:00 – 9:45pm Time zone: Asia/Kolkata Google Meet joining info Video call link: https://meet.google.com/weg-zbky-ggz Or dial: ‪(US) +1 864-688-9805‬ PIN: ‪929 415 446‬# More phone numbers: https://tel.meet/weg-zbky-ggz?pin=4234732411175 | B440: dheu-2.myshopify.com | C440: Dheu | E440: https://meet.google.com/weg-zbky-ggz
A441: Hi @919537616197, sharing the meeting link here: Mortantra <> BiteSpeed | support Dashboard Training Saturday, 23 August · 1:30 – 2:15pm Time zone: Asia/Kolkata Google Meet joining info Video call link: https://meet.google.com/ovc-zemi-ynj Or dial: ‪(US) +1 401-552-4759‬ PIN: ‪214 099 771‬# More phone numbers: https://tel.meet/ovc-zemi-ynj?pin=4184988866118 | B441: mortantra-store.myshopify.com | C441: Mortantra <> BiteSpeed | E441: https://meet.google.com/ovc-zemi-ynj
A442: Bitamin <> BiteSpeed | WA set up + Zoko balance Friday, August 22 · 5:00 – 5:30pm Time zone: Asia/Kolkata Google Meet joining info Video call link: https://meet.google.com/wcu-emuo-yig Or dial: ‪(US) +1 252-574-6173‬ PIN: ‪883 018 552‬# More phone numbers: https://tel.meet/wcu-emuo-yig?pin=2487770155832 | B442: b7abe7-2.myshopify.com | C442: Bitamin | E442: https://meet.google.com/wcu-emuo-yig
A443: Hi @919737779510, I am on the call now, can we connect? https://meet.google.com/noh-zwrv-awe?authuser=0 | C443: Anant Exports <> BiteSpeed | E443: https://meet.google.com/noh-zwrv-awe
A444: Hi @919737779510, I am on the call now, can we connect? https://meet.google.com/noh-zwrv-awe?authuser=0 | C444: Anant Exports <> BiteSpeed | E444: https://meet.google.com/noh-zwrv-awe
A445: Beegle <> BiteSpeed Friday, August 22 · 12:00 – 12:30pm Time zone: Asia/Kolkata Google Meet joining info Video call link: https://meet.google.com/deo-pvrb-rkh Or dial: ‪(US) +1 475-355-7061‬ PIN: ‪658 891 478‬# More phone numbers: https://tel.meet/deo-pvrb-rkh?pin=3023206629606 | B445: beeglee-in.myshopify.com | C445: Beeglee <> BiteSpeed | E445: https://meet.google.com/deo-pvrb-rkh
...
